{"Case": "Limited Edition Item", "NumSteamListings": 0, "IsBuff": false, "IsSkinport": false, "IsCSFloat": false, "ISTradeit": false, "ImageUrl": "https://cs2.cdn.cashtrader.pro/econ/default_generated/weapon_deagle_aq_deagle_case_hardened_2_light.png", "Profit": 0.03, "ProfitPercents": {"Classified": 0.03}, "PercentReceive": {"Classified": 1}, "CaseCost": 10, "KeyCost": 0, "ROI": 0.5231399999999999, "RarityROIPercents": {"Classified": 1}, "RarityValue": {"Classified": 5.2314}, "IsCaseEstimate": false, "KnifeCosts": null, "ItemCosts": {"Classified": {"Desert Eagle | Heat Treated": {"FactoryNew": 26.419999999999998, "MinimalWear": 7.130000000000001, "FieldTested": 5, "WellWorn": 2.87, "BattleScarred": 2.43, "totalItemValue": 5.2314}}}, "Items": {"Desert Eagle | Heat Treated": {"Name": "Desert Eagle | Heat Treated", "FloatMin": 0, "FloatMax": 100, "ImageUrl": "https://cs2.cdn.cashtrader.pro/econ/default_generated/weapon_deagle_aq_deagle_case_hardened_2_light.png", "Variations": 0, "Rarity": 8, "IsKnife": false, "ItemCollectionId": 336}}, "SouvenirPackId": null, "SouvenirPackName": null, "SouvenirPackImg": null}