{"Case": "The Dust Collection", "NumSteamListings": 0, "IsBuff": false, "IsSkinport": true, "IsCSFloat": false, "ISTradeit": false, "ImageUrl": "https://steamcdn-a.akamaihd.net/apps/730/icons/econ/default_generated/weapon_deagle_aa_flames_light_large.dd140c3b359c16ccd8e918ca6ad0b2628151fe1c.png", "Profit": 0.9999144444444444, "ProfitPercents": {"Restricted": 0.03333333333333333, "Mil_Spec": 0.16666111111111112, "Industrial": 0.79992}, "PercentReceive": {"Restricted": 0.03333333333333333, "Mil_Spec": 0.16666666666666666, "Industrial": 0.8}, "CaseCost": 0.01, "KeyCost": 0, "ROI": 3935.429548888889, "RarityROIPercents": {"Restricted": 0.16436380006807183, "Mil_Spec": 0.4264092002715319, "Industrial": 0.4092269996603963}, "RarityValue": {"Restricted": 194.05264666666662, "Mil_Spec": 100.686202, "Industrial": 20.13105033333333}, "IsCaseEstimate": false, "KnifeCosts": null, "ItemCosts": {"Restricted": {"Desert Eagle | Blaze": {"FactoryNew": 553.7299999999999, "MinimalWear": 644.76, "totalItemValue": 557.0981099999999}, "Glock-18 | Brass": {"FactoryNew": 68.85000000000001, "MinimalWear": 29.389999999999997, "FieldTested": 14.52, "WellWorn": 16.28, "BattleScarred": 16.45, "totalItemValue": 20.4499}, "P2000 | Scorpion": {"FactoryNew": 4.17, "MinimalWear": 16.06, "totalItemValue": 4.609929999999999}}, "Mil_Spec": {"AUG | Copperhead": {"MinimalWear": 110.03999999999999, "FieldTested": 104.00999999999999, "totalItemValue": 104.922339}, "AWP | Snake Camo": {"FactoryNew": 202.89, "MinimalWear": 87.88, "FieldTested": 100.81, "WellWorn": 96.80999999999999, "BattleScarred": 93.82, "totalItemValue": 97.89426700000001}, "Sawed-Off | Copper": {"FactoryNew": 122.78999999999999, "MinimalWear": 109.99, "FieldTested": 100.55, "WellWorn": 87.78, "BattleScarred": 93.19999999999999, "totalItemValue": 99.24199999999999}}, "Industrial": {"SCAR-20 | Palm": {"FactoryNew": 43.809999999999995, "MinimalWear": 20.98, "FieldTested": 21.72, "WellWorn": 19.16, "BattleScarred": 18.7, "totalItemValue": 21.068686}, "M4A4 | Desert Storm": {"FactoryNew": 30.57, "MinimalWear": 23.64, "FieldTested": 17.59, "WellWorn": 16.28, "BattleScarred": 19.72, "totalItemValue": 18.853651999999997}, "AK-47 | Predator": {"FactoryNew": 58.63, "MinimalWear": 24.95, "FieldTested": 18.9, "WellWorn": 24.130000000000003, "BattleScarred": 17.91, "totalItemValue": 20.470813}}}, "Items": {"Desert Eagle | Blaze": {"Name": "Desert Eagle | Blaze", "FloatMin": 0, "FloatMax": 8, "ImageUrl": "https://steamcdn-a.akamaihd.net/apps/730/icons/econ/default_generated/weapon_deagle_aa_flames_light_large.dd140c3b359c16ccd8e918ca6ad0b2628151fe1c.png", "Variations": 0, "Rarity": 5, "IsKnife": false, "ItemCollectionId": 57}, "Glock-18 | Brass": {"Name": "Glock-18 | Brass", "FloatMin": 0, "FloatMax": 100, "ImageUrl": "https://steamcdn-a.akamaihd.net/apps/730/icons/econ/default_generated/weapon_glock_aq_brass_light_large.c9fbb8483ca7b5859fafc3c8fe495b3d396205dd.png", "Variations": 0, "Rarity": 5, "IsKnife": false, "ItemCollectionId": 57}, "P2000 | Scorpion": {"Name": "P2000 | Scorpion", "FloatMin": 0, "FloatMax": 8, "ImageUrl": "https://steamcdn-a.akamaihd.net/apps/730/icons/econ/default_generated/weapon_hkp2000_am_scorpion_p2000_light_large.86333a595bc6c6139a4e84734e6eb88cd33d3e14.png", "Variations": 0, "Rarity": 5, "IsKnife": false, "ItemCollectionId": 57}, "AUG | Copperhead": {"Name": "AUG | Copperhead", "FloatMin": 12, "FloatMax": 38, "ImageUrl": "https://steamcdn-a.akamaihd.net/apps/730/icons/econ/default_generated/weapon_aug_hy_copperhead_light_large.166fd555b0075feb698783999d906c4529d2d631.png", "Variations": 0, "Rarity": 2, "IsKnife": false, "ItemCollectionId": 57}, "AWP | Snake Camo": {"Name": "AWP | Snake Camo", "FloatMin": 6, "FloatMax": 80, "ImageUrl": "https://steamcdn-a.akamaihd.net/apps/730/icons/econ/default_generated/weapon_awp_sp_snake_light_large.c0b327d960af85c987bed944287935fb4b6a780a.png", "Variations": 0, "Rarity": 2, "IsKnife": false, "ItemCollectionId": 57}, "Sawed-Off | Copper": {"Name": "Sawed-Off | Copper", "FloatMin": 0, "FloatMax": 100, "ImageUrl": "https://steamcdn-a.akamaihd.net/apps/730/icons/econ/default_generated/weapon_sawedoff_aq_copper_light_large.a2d3d9236120109adf8df1bc53b7d02250f6a50a.png", "Variations": 0, "Rarity": 2, "IsKnife": false, "ItemCollectionId": 57}, "SCAR-20 | Palm": {"Name": "SCAR-20 | Palm", "FloatMin": 6, "FloatMax": 80, "ImageUrl": "https://steamcdn-a.akamaihd.net/apps/730/icons/econ/default_generated/weapon_scar20_sp_palm_light_large.ed935d932711961605c3b03b896560f4ebfe8861.png", "Variations": 0, "Rarity": 1, "IsKnife": false, "ItemCollectionId": 57}, "M4A4 | Desert Storm": {"Name": "M4A4 | Desert Storm", "FloatMin": 6, "FloatMax": 80, "ImageUrl": "https://steamcdn-a.akamaihd.net/apps/730/icons/econ/default_generated/weapon_m4a1_hy_desert_light_large.30d1e3dcc03baca8d4a3f222b3b851ad12c77799.png", "Variations": 0, "Rarity": 1, "IsKnife": false, "ItemCollectionId": 57}, "AK-47 | Predator": {"Name": "AK-47 | Predator", "FloatMin": 6, "FloatMax": 80, "ImageUrl": "https://steamcdn-a.akamaihd.net/apps/730/icons/econ/default_generated/weapon_ak47_sp_zebracam_light_large.5f15c9e41b9ac135b87cdadb407c9872e31c1f29.png", "Variations": 0, "Rarity": 1, "IsKnife": false, "ItemCollectionId": 57}}, "SouvenirPackId": null, "SouvenirPackName": null, "SouvenirPackImg": null}