{"Case": "CS:GO Weapon Case 2", "NumSteamListings": 828, "IsBuff": false, "IsSkinport": false, "IsCSFloat": false, "ISTradeit": true, "ImageUrl": "https://steamcommunity-a.akamaihd.net/economy/image/-9a81dlWLwJ2UUGcVs_nsVtzdOEdtWwKGZZLQHTxDZ7I56KU0Zwwo4NUX4oFJZEHLbXU5A1PIYQNqhpOSV-fRPasw8rsRVx4MwFo5PT8elUwgKKZJmtEvo_kxITZk6StNe-Fz2pTu8Aj3eqVpIqgjVfjrRI9fSmtc1Nw-Kh3/256fx256f", "Profit": 0.05807640625614795, "ProfitPercents": {"Covert": 0.00639386189258312, "Classified": 0.031969309462915596, "Restricted": 0.017063618925831203, "Mil_Spec": 9.271099744245525e-05, "Contraband": 0.0025569049773755703}, "PercentReceive": {"Contraband": 0.0025575447570332483, "Covert": 0.00639386189258312, "Classified": 0.0319693094629156, "Restricted": 0.159846547314578, "Mil_Spec": 0.7992327365728901}, "CaseCost": 22.98, "KeyCost": 3.05, "ROI": 0.6032285536524716, "RarityROIPercents": {"Contraband": 0.12835815090808944, "Covert": 0.03685374935609029, "Classified": 0.18010822701023468, "Restricted": 0.1964267606964925, "Mil_Spec": 0.45825311202909313}, "RarityValue": {"Covert": 79.90065536, "Classified": 78.096615, "Restricted": 17.034496824999998, "Mil_Spec": 7.948113744, "Contraband": 695.7162132446153}, "IsCaseEstimate": false, "KnifeCosts": {"Bayonet | Fade": {"FactoryNew": 1192.35, "StatTrak\u2122 FactoryNew": 1264.8999999999999, "MinimalWear": 848.6399999999999, "StatTrak\u2122 MinimalWear": 833.7959999999999, "totalItemValue": 1186.5643722}, "Bayonet | \u2605 (Vanilla)": {"totalItemValue": 743.4979999999999, "Normal": 745.66, "StatTrak\u2122 Normal": 724.04}, "Bayonet | Slaughter": {"FactoryNew": 901.4699999999999, "StatTrak\u2122 FactoryNew": 1021.85, "MinimalWear": 757.28, "StatTrak\u2122 MinimalWear": 781.17, "FieldTested": 641.55, "StatTrak\u2122 FieldTested": 466.932, "totalItemValue": 801.98647368}, "Bayonet | Case Hardened": {"FactoryNew": 951.2199999999999, "StatTrak\u2122 FactoryNew": 816.66, "MinimalWear": 626.48, "StatTrak\u2122 MinimalWear": 707.4399999999999, "FieldTested": 544.81, "StatTrak\u2122 FieldTested": 594.01, "WellWorn": 515.62, "StatTrak\u2122 WellWorn": 539.84, "BattleScarred": 501.51000000000005, "StatTrak\u2122 BattleScarred": 557.8199999999999, "totalItemValue": 567.3147}, "Bayonet | Crimson Web": {"FactoryNew": 2332.9799999999996, "StatTrak\u2122 FactoryNew": 0, "MinimalWear": 753.03, "StatTrak\u2122 MinimalWear": 609.504, "FieldTested": 449.55999999999995, "StatTrak\u2122 FieldTested": 517.6999999999999, "WellWorn": 425.14, "StatTrak\u2122 WellWorn": 341.856, "BattleScarred": 412.60999999999996, "StatTrak\u2122 BattleScarred": 442.09, "totalItemValue": 503.69309262}, "Bayonet | Night": {"FactoryNew": 1447.6399999999999, "StatTrak\u2122 FactoryNew": 0, "MinimalWear": 470.57, "StatTrak\u2122 MinimalWear": 509.06, "FieldTested": 339.86, "StatTrak\u2122 FieldTested": 331.03, "WellWorn": 325.34, "StatTrak\u2122 WellWorn": 289.29999999999995, "BattleScarred": 303.34, "StatTrak\u2122 BattleScarred": 234.95999999999998, "totalItemValue": 359.6348247}, "Bayonet | Blue Steel": {"FactoryNew": 775.17, "StatTrak\u2122 FactoryNew": 310.44, "MinimalWear": 556.61, "StatTrak\u2122 MinimalWear": 538.33, "FieldTested": 521.66, "StatTrak\u2122 FieldTested": 477.97999999999996, "WellWorn": 466.04999999999995, "StatTrak\u2122 WellWorn": 451.53999999999996, "BattleScarred": 429.7, "StatTrak\u2122 BattleScarred": 312.50399999999996, "totalItemValue": 504.095574}, "Bayonet | Stained": {"FactoryNew": 393.38399999999996, "StatTrak\u2122 FactoryNew": 426.072, "MinimalWear": 418.79999999999995, "StatTrak\u2122 MinimalWear": 316.008, "FieldTested": 399.16999999999996, "StatTrak\u2122 FieldTested": 382.76, "WellWorn": 361.7, "StatTrak\u2122 WellWorn": 499.488, "BattleScarred": 350.44, "StatTrak\u2122 BattleScarred": 249.88799999999998, "totalItemValue": 385.705626}, "Bayonet | Boreal Forest": {"FactoryNew": 366.70799999999997, "StatTrak\u2122 FactoryNew": 310.44, "MinimalWear": 360.15, "StatTrak\u2122 MinimalWear": 271.488, "FieldTested": 294.75, "StatTrak\u2122 FieldTested": 312.38, "WellWorn": 275.59, "StatTrak\u2122 WellWorn": 266.82, "BattleScarred": 278.9, "StatTrak\u2122 BattleScarred": 315.96999999999997, "totalItemValue": 302.08668018000003}, "Bayonet | Urban Masked": {"FactoryNew": 383.544, "StatTrak\u2122 FactoryNew": 308.31600000000003, "MinimalWear": 360.67, "StatTrak\u2122 MinimalWear": 376.39, "FieldTested": 299.59, "StatTrak\u2122 FieldTested": 225.64, "WellWorn": 282.68, "StatTrak\u2122 WellWorn": 294.5, "BattleScarred": 297.95, "StatTrak\u2122 BattleScarred": 200.11199999999997, "totalItemValue": 303.02757858}, "Bayonet | Forest DDPAT": {"FactoryNew": 383.544, "StatTrak\u2122 FactoryNew": 0, "MinimalWear": 354.74999999999994, "StatTrak\u2122 MinimalWear": 368.12, "FieldTested": 298.23, "StatTrak\u2122 FieldTested": 286.32, "WellWorn": 285.52, "StatTrak\u2122 WellWorn": 268.52, "BattleScarred": 297.34, "StatTrak\u2122 BattleScarred": 220.12800000000001, "totalItemValue": 304.91307886}, "Bayonet | Scorched": {"FactoryNew": 367.83, "StatTrak\u2122 FactoryNew": 0, "MinimalWear": 353.27, "StatTrak\u2122 MinimalWear": 348.75, "FieldTested": 298.21999999999997, "StatTrak\u2122 FieldTested": 353.88, "WellWorn": 289.48, "StatTrak\u2122 WellWorn": 233.29199999999997, "BattleScarred": 294.64, "StatTrak\u2122 BattleScarred": 227.12, "totalItemValue": 308.07464172000005}, "Bayonet | Safari Mesh": {"FactoryNew": 501.1499999999999, "StatTrak\u2122 FactoryNew": 385.728, "MinimalWear": 312.93, "StatTrak\u2122 MinimalWear": 317.68, "FieldTested": 290.74, "StatTrak\u2122 FieldTested": 276.99, "WellWorn": 269.03, "StatTrak\u2122 WellWorn": 285.05, "BattleScarred": 289.29999999999995, "StatTrak\u2122 BattleScarred": 176.54999999999998, "totalItemValue": 291.23317044}, "Flip Knife | Fade": {"FactoryNew": 1071.6899999999998, "StatTrak\u2122 FactoryNew": 966.23, "MinimalWear": 958.7879999999999, "StatTrak\u2122 MinimalWear": 685.548, "totalItemValue": 1056.34584}, "Flip Knife | Slaughter": {"FactoryNew": 714.31, "StatTrak\u2122 FactoryNew": 691.6, "MinimalWear": 640.6899999999999, "StatTrak\u2122 MinimalWear": 611.4, "FieldTested": 605.17, "StatTrak\u2122 FieldTested": 457.78999999999996, "totalItemValue": 660.5577183999999}, "Flip Knife | Crimson Web": {"FactoryNew": 1917.7439999999997, "StatTrak\u2122 FactoryNew": 0, "MinimalWear": 684.49, "StatTrak\u2122 MinimalWear": 657.1899999999999, "FieldTested": 435.65, "StatTrak\u2122 FieldTested": 464.99999999999994, "WellWorn": 401.55999999999995, "StatTrak\u2122 WellWorn": 281.82, "BattleScarred": 337.37, "StatTrak\u2122 BattleScarred": 275.15999999999997, "totalItemValue": 467.12728618}, "Flip Knife | Case Hardened": {"FactoryNew": 668.06, "StatTrak\u2122 FactoryNew": 583.6560000000001, "MinimalWear": 405.252, "StatTrak\u2122 MinimalWear": 434.16999999999996, "FieldTested": 380.8, "StatTrak\u2122 FieldTested": 410.77000000000004, "WellWorn": 370.26, "StatTrak\u2122 WellWorn": 328.09, "BattleScarred": 319.57, "StatTrak\u2122 BattleScarred": 347.89, "totalItemValue": 383.83075}, "Flip Knife | \u2605 (Vanilla)": {"totalItemValue": 523.6916000000001, "Normal": 525.984, "StatTrak\u2122 Normal": 503.06}, "Flip Knife | Urban Masked": {"FactoryNew": 229.95999999999998, "StatTrak\u2122 FactoryNew": 4769.61, "MinimalWear": 261.78999999999996, "StatTrak\u2122 MinimalWear": 244.20999999999998, "FieldTested": 244.98999999999998, "StatTrak\u2122 FieldTested": 234.42, "WellWorn": 243.18999999999997, "StatTrak\u2122 WellWorn": 106.48999999999998, "BattleScarred": 218.12, "StatTrak\u2122 BattleScarred": 170.1, "totalItemValue": 243.55971060000002}, "Flip Knife | Night": {"FactoryNew": 511.76, "StatTrak\u2122 FactoryNew": 0, "MinimalWear": 354.98, "StatTrak\u2122 MinimalWear": 383.72999999999996, "FieldTested": 269.42999999999995, "StatTrak\u2122 FieldTested": 271.04, "WellWorn": 273.81, "StatTrak\u2122 WellWorn": 215.42, "BattleScarred": 256.79999999999995, "StatTrak\u2122 BattleScarred": 261.53, "totalItemValue": 283.5313481}, "Flip Knife | Blue Steel": {"FactoryNew": 477.36999999999995, "StatTrak\u2122 FactoryNew": 383.544, "MinimalWear": 382, "StatTrak\u2122 MinimalWear": 387.35999999999996, "FieldTested": 356.27, "StatTrak\u2122 FieldTested": 275.15999999999997, "WellWorn": 366.53, "StatTrak\u2122 WellWorn": 258.47999999999996, "BattleScarred": 355.28, "StatTrak\u2122 BattleScarred": 239.30399999999997, "totalItemValue": 361.103916}, "Flip Knife | Stained": {"FactoryNew": 253.98, "StatTrak\u2122 FactoryNew": 283.32, "MinimalWear": 309.44, "StatTrak\u2122 MinimalWear": 290.44, "FieldTested": 270.65, "StatTrak\u2122 FieldTested": 293.81, "WellWorn": 256.15, "StatTrak\u2122 WellWorn": 183.432, "BattleScarred": 260.37, "StatTrak\u2122 BattleScarred": 275.808, "totalItemValue": 273.232776}, "Flip Knife | Safari Mesh": {"FactoryNew": 324.74, "StatTrak\u2122 FactoryNew": 310.44, "MinimalWear": 221.93999999999997, "StatTrak\u2122 MinimalWear": 238.65999999999997, "FieldTested": 214.51, "StatTrak\u2122 FieldTested": 209.20999999999998, "WellWorn": 209.5, "StatTrak\u2122 WellWorn": 160.09199999999998, "BattleScarred": 220.07999999999998, "StatTrak\u2122 BattleScarred": 157.58399999999997, "totalItemValue": 215.33052376}, "Flip Knife | Boreal Forest": {"FactoryNew": 335.89, "StatTrak\u2122 FactoryNew": 0, "MinimalWear": 239.95999999999998, "StatTrak\u2122 MinimalWear": 270.91, "FieldTested": 223.29, "StatTrak\u2122 FieldTested": 246.31, "WellWorn": 214.21999999999997, "StatTrak\u2122 WellWorn": 148.44, "BattleScarred": 221.2, "StatTrak\u2122 BattleScarred": 210.83, "totalItemValue": 226.5510298}, "Flip Knife | Forest DDPAT": {"FactoryNew": 442.66799999999995, "StatTrak\u2122 FactoryNew": 0, "MinimalWear": 242.10999999999999, "StatTrak\u2122 MinimalWear": 257.5, "FieldTested": 222.47, "StatTrak\u2122 FieldTested": 244.23000000000002, "WellWorn": 216.91, "StatTrak\u2122 WellWorn": 169.18999999999997, "BattleScarred": 218.94, "StatTrak\u2122 BattleScarred": 249.72, "totalItemValue": 227.30776265999998}, "Flip Knife | Scorched": {"FactoryNew": 261.14399999999995, "StatTrak\u2122 FactoryNew": 310.44, "MinimalWear": 272.09, "StatTrak\u2122 MinimalWear": 269.75, "FieldTested": 240.74, "StatTrak\u2122 FieldTested": 234.67, "WellWorn": 161.676, "StatTrak\u2122 WellWorn": 174.04999999999998, "BattleScarred": 229.62, "StatTrak\u2122 BattleScarred": 183.432, "totalItemValue": 236.47655974000003}, "Gut Knife | Fade": {"FactoryNew": 347.14, "StatTrak\u2122 FactoryNew": 409.15, "MinimalWear": 361.97999999999996, "StatTrak\u2122 MinimalWear": 322.39, "totalItemValue": 353.51415999999995}, "Gut Knife | Case Hardened": {"FactoryNew": 500.28, "StatTrak\u2122 FactoryNew": 366.45, "MinimalWear": 245.25999999999996, "StatTrak\u2122 MinimalWear": 289.19, "FieldTested": 230.89, "StatTrak\u2122 FieldTested": 262.45, "WellWorn": 216.35, "StatTrak\u2122 WellWorn": 262.99, "BattleScarred": 213.57, "StatTrak\u2122 BattleScarred": 237.79, "totalItemValue": 239.36088999999998}, "Gut Knife | Crimson Web": {"FactoryNew": 547.4159999999999, "StatTrak\u2122 FactoryNew": 0, "MinimalWear": 243.8, "StatTrak\u2122 MinimalWear": 388.58, "FieldTested": 167.66, "StatTrak\u2122 FieldTested": 187.85, "WellWorn": 175.57, "StatTrak\u2122 WellWorn": 82.6, "BattleScarred": 164.07, "StatTrak\u2122 BattleScarred": 173.33, "totalItemValue": 185.35960962}, "Gut Knife | Slaughter": {"FactoryNew": 284.98999999999995, "StatTrak\u2122 FactoryNew": 318.4, "MinimalWear": 238.95999999999998, "StatTrak\u2122 MinimalWear": 188.424, "FieldTested": 222.88, "StatTrak\u2122 FieldTested": 246.32999999999998, "totalItemValue": 253.99993944}, "Gut Knife | \u2605 (Vanilla)": {"totalItemValue": 204.732, "Normal": 206.33999999999997, "StatTrak\u2122 Normal": 190.26}, "Gut Knife | Urban Masked": {"FactoryNew": 138.40800000000002, "StatTrak\u2122 FactoryNew": 157.488, "MinimalWear": 144.55999999999997, "StatTrak\u2122 MinimalWear": 169.51, "FieldTested": 153.57, "StatTrak\u2122 FieldTested": 151.39, "WellWorn": 154.26, "StatTrak\u2122 WellWorn": 156.648, "BattleScarred": 156.23999999999998, "StatTrak\u2122 BattleScarred": 143.1, "totalItemValue": 152.53393078}, "Gut Knife | Safari Mesh": {"FactoryNew": 487.76399999999995, "StatTrak\u2122 FactoryNew": 0, "MinimalWear": 155.80999999999997, "StatTrak\u2122 MinimalWear": 110.892, "FieldTested": 155.54, "StatTrak\u2122 FieldTested": 156.23999999999998, "WellWorn": 148.64999999999998, "StatTrak\u2122 WellWorn": 33.699999999999996, "BattleScarred": 140.37, "StatTrak\u2122 BattleScarred": 86.47999999999999, "totalItemValue": 151.96880926}, "Gut Knife | Blue Steel": {"FactoryNew": 220.11999999999998, "StatTrak\u2122 FactoryNew": 333.6, "MinimalWear": 176.8, "StatTrak\u2122 MinimalWear": 214.82, "FieldTested": 171.93, "StatTrak\u2122 FieldTested": 204.26, "WellWorn": 169.94, "StatTrak\u2122 WellWorn": 216.456, "BattleScarred": 169.67, "StatTrak\u2122 BattleScarred": 161.82999999999998, "totalItemValue": 177.01605400000003}, "Gut Knife | Night": {"FactoryNew": 507.47999999999996, "StatTrak\u2122 FactoryNew": 0, "MinimalWear": 168.76, "StatTrak\u2122 MinimalWear": 173.556, "FieldTested": 149.91, "StatTrak\u2122 FieldTested": 163.992, "WellWorn": 104.79, "StatTrak\u2122 WellWorn": 71.22, "BattleScarred": 145.26, "StatTrak\u2122 BattleScarred": 154.87, "totalItemValue": 150.85677564000002}, "Gut Knife | Stained": {"FactoryNew": 200.10000000000002, "StatTrak\u2122 FactoryNew": 611.8599999999999, "MinimalWear": 166.38, "StatTrak\u2122 MinimalWear": 160.09199999999998, "FieldTested": 159.2, "StatTrak\u2122 FieldTested": 120.89999999999999, "WellWorn": 162.26999999999998, "StatTrak\u2122 WellWorn": 176.052, "BattleScarred": 155.79999999999998, "StatTrak\u2122 BattleScarred": 163.89, "totalItemValue": 162.623676}, "Gut Knife | Forest DDPAT": {"FactoryNew": 263.38800000000003, "StatTrak\u2122 FactoryNew": 0, "MinimalWear": 166.07999999999998, "StatTrak\u2122 MinimalWear": 129.08999999999997, "FieldTested": 139.36999999999998, "StatTrak\u2122 FieldTested": 152.52, "WellWorn": 150.75599999999997, "StatTrak\u2122 WellWorn": 135.5, "BattleScarred": 150.38, "StatTrak\u2122 BattleScarred": 156.72, "totalItemValue": 147.06793969999998}, "Gut Knife | Scorched": {"FactoryNew": 260.2, "StatTrak\u2122 FactoryNew": 0, "MinimalWear": 163.04, "StatTrak\u2122 MinimalWear": 117.47999999999999, "FieldTested": 147.84, "StatTrak\u2122 FieldTested": 147.23, "WellWorn": 154.32, "StatTrak\u2122 WellWorn": 126.34, "BattleScarred": 134.1, "StatTrak\u2122 BattleScarred": 149.72, "totalItemValue": 148.691665}, "Gut Knife | Boreal Forest": {"FactoryNew": 341.68, "StatTrak\u2122 FactoryNew": 310.44, "MinimalWear": 179.86999999999998, "StatTrak\u2122 MinimalWear": 177.048, "FieldTested": 139.94, "StatTrak\u2122 FieldTested": 147.69, "WellWorn": 149.7, "StatTrak\u2122 WellWorn": 55.10999999999999, "BattleScarred": 155.89, "StatTrak\u2122 BattleScarred": 120.52999999999999, "totalItemValue": 149.92419311999998}, "Karambit | Slaughter": {"FactoryNew": 2101.3599999999997, "StatTrak\u2122 FactoryNew": 1417.464, "MinimalWear": 1759.3299999999997, "StatTrak\u2122 MinimalWear": 1267.3799999999999, "FieldTested": 1183.9199999999998, "StatTrak\u2122 FieldTested": 1133.964, "totalItemValue": 1766.77094376}, "Karambit | \u2605 (Vanilla)": {"totalItemValue": 2001.7549999999997, "Normal": 1991.8299999999997, "StatTrak\u2122 Normal": 2091.08}, "Karambit | Case Hardened": {"FactoryNew": 1917.7439999999997, "StatTrak\u2122 FactoryNew": 3705.7439999999997, "MinimalWear": 1142.3039999999999, "StatTrak\u2122 MinimalWear": 1775.1799999999998, "FieldTested": 1440.05, "StatTrak\u2122 FieldTested": 998.556, "WellWorn": 913.3439999999999, "StatTrak\u2122 WellWorn": 1243.4999999999998, "BattleScarred": 1095.9399999999998, "StatTrak\u2122 BattleScarred": 845.3039999999999, "totalItemValue": 1211.35203}, "Karambit | Crimson Web": {"FactoryNew": 6670.4039999999995, "StatTrak\u2122 FactoryNew": 6100.24, "MinimalWear": 1417.464, "StatTrak\u2122 MinimalWear": 1908.07, "FieldTested": 1335.7599999999998, "StatTrak\u2122 FieldTested": 1262.95, "WellWorn": 1187.2499999999998, "StatTrak\u2122 WellWorn": 865.068, "BattleScarred": 1056.32, "StatTrak\u2122 BattleScarred": 792.0239999999999, "totalItemValue": 1324.5785770399998}, "Karambit | Blue Steel": {"FactoryNew": 1315.4039999999998, "StatTrak\u2122 FactoryNew": 2236.182, "MinimalWear": 1520.7499999999998, "StatTrak\u2122 MinimalWear": 1217.1839999999997, "FieldTested": 1469.54, "StatTrak\u2122 FieldTested": 992.2199999999998, "WellWorn": 1337.19, "StatTrak\u2122 WellWorn": 1317.6699999999998, "BattleScarred": 1339.7099999999998, "StatTrak\u2122 BattleScarred": 948.4439999999998, "totalItemValue": 1397.6659739999998}, "Karambit | Stained": {"FactoryNew": 1033.752, "StatTrak\u2122 FactoryNew": 1486.99, "MinimalWear": 1202.9699999999998, "StatTrak\u2122 MinimalWear": 833.7959999999999, "FieldTested": 1167.4799999999998, "StatTrak\u2122 FieldTested": 792.108, "WellWorn": 1063.7199999999998, "StatTrak\u2122 WellWorn": 759.588, "BattleScarred": 991.73, "StatTrak\u2122 BattleScarred": 714.8159999999999, "totalItemValue": 1087.3458299999998}, "Karambit | Night": {"FactoryNew": 1723.1279999999997, "StatTrak\u2122 FactoryNew": 310.44, "MinimalWear": 875.208, "StatTrak\u2122 MinimalWear": 1121.9499999999998, "FieldTested": 1031.8999999999999, "StatTrak\u2122 FieldTested": 1019.36, "WellWorn": 1022.0699999999999, "StatTrak\u2122 WellWorn": 709.812, "BattleScarred": 960.03, "StatTrak\u2122 BattleScarred": 696.972, "totalItemValue": 994.7506073799999}, "Karambit | Boreal Forest": {"FactoryNew": 2044.0599999999997, "StatTrak\u2122 FactoryNew": 4769.61, "MinimalWear": 886.9399999999999, "StatTrak\u2122 MinimalWear": 931.4899999999999, "FieldTested": 849.9399999999999, "StatTrak\u2122 FieldTested": 810.3599999999999, "WellWorn": 570.156, "StatTrak\u2122 WellWorn": 759.25, "BattleScarred": 564.9, "StatTrak\u2122 BattleScarred": 566.904, "totalItemValue": 799.5068050799999}, "Karambit | Urban Masked": {"FactoryNew": 841.8, "StatTrak\u2122 FactoryNew": 0, "MinimalWear": 947.8799999999999, "StatTrak\u2122 MinimalWear": 673.716, "FieldTested": 867.4499999999999, "StatTrak\u2122 FieldTested": 836.36, "WellWorn": 795.01, "StatTrak\u2122 WellWorn": 583.4759999999999, "BattleScarred": 798.52, "StatTrak\u2122 BattleScarred": 575.328, "totalItemValue": 852.50135958}, "Karambit | Scorched": {"FactoryNew": 793.4399999999999, "StatTrak\u2122 FactoryNew": 0, "MinimalWear": 899.5299999999999, "StatTrak\u2122 MinimalWear": 678.636, "FieldTested": 906.2599999999999, "StatTrak\u2122 FieldTested": 607.0079999999999, "WellWorn": 879.9699999999999, "StatTrak\u2122 WellWorn": 759.5899999999999, "BattleScarred": 817.1499999999999, "StatTrak\u2122 BattleScarred": 589.164, "totalItemValue": 863.2477728799998}, "Karambit | Forest DDPAT": {"FactoryNew": 839.9519999999999, "StatTrak\u2122 FactoryNew": 0, "MinimalWear": 881.28, "StatTrak\u2122 MinimalWear": 625.332, "FieldTested": 849.03, "StatTrak\u2122 FieldTested": 795.14, "WellWorn": 565.3199999999999, "StatTrak\u2122 WellWorn": 563.568, "BattleScarred": 774.4, "StatTrak\u2122 BattleScarred": 576.1560000000001, "totalItemValue": 807.48767436}, "Karambit | Safari Mesh": {"FactoryNew": 833.6399999999999, "StatTrak\u2122 FactoryNew": 0, "MinimalWear": 858.8799999999999, "StatTrak\u2122 MinimalWear": 647.8679999999999, "FieldTested": 833.53, "StatTrak\u2122 FieldTested": 759.5699999999999, "WellWorn": 766.78, "StatTrak\u2122 WellWorn": 563.9879999999999, "BattleScarred": 560.064, "StatTrak\u2122 BattleScarred": 555.816, "totalItemValue": 783.0440545199999}, "Karambit | Fade": {"FactoryNew": 3000.0119999999997, "StatTrak\u2122 FactoryNew": 2726.3639999999996, "MinimalWear": 2768.0519999999997, "StatTrak\u2122 MinimalWear": 310.44, "totalItemValue": 2955.9840131999995}, "M9 Bayonet | Fade": {"FactoryNew": 2157.8759999999997, "StatTrak\u2122 FactoryNew": 1950.84, "MinimalWear": 2001.1199999999997, "StatTrak\u2122 MinimalWear": 2000.952, "totalItemValue": 2132.1378395999996}, "M9 Bayonet | \u2605 (Vanilla)": {"totalItemValue": 1972.326, "Normal": 1998.6, "StatTrak\u2122 Normal": 1735.86}, "M9 Bayonet | Slaughter": {"FactoryNew": 1357.26, "StatTrak\u2122 FactoryNew": 1300.7279999999998, "MinimalWear": 1677.1999999999998, "StatTrak\u2122 MinimalWear": 1108.956, "FieldTested": 1361.8999999999999, "StatTrak\u2122 FieldTested": 962.2079999999999, "totalItemValue": 1476.6385660800001}, "M9 Bayonet | Crimson Web": {"FactoryNew": 6874.23, "StatTrak\u2122 FactoryNew": 13230.89, "MinimalWear": 2055.4, "StatTrak\u2122 MinimalWear": 1363.3439999999998, "FieldTested": 1140.83, "StatTrak\u2122 FieldTested": 1094.84, "WellWorn": 977.2899999999998, "StatTrak\u2122 WellWorn": 717.048, "BattleScarred": 971.9199999999998, "StatTrak\u2122 BattleScarred": 677.9639999999999, "totalItemValue": 1271.13986618}, "M9 Bayonet | Case Hardened": {"FactoryNew": 1350.7559999999999, "StatTrak\u2122 FactoryNew": 2001.1199999999997, "MinimalWear": 1311.53, "StatTrak\u2122 MinimalWear": 1281.8899999999999, "FieldTested": 820.4639999999999, "StatTrak\u2122 FieldTested": 1074.7199999999998, "WellWorn": 1033.8799999999999, "StatTrak\u2122 WellWorn": 738.9119999999999, "BattleScarred": 978.4399999999999, "StatTrak\u2122 BattleScarred": 679.8839999999999, "totalItemValue": 1028.498652}, "M9 Bayonet | Scorched": {"FactoryNew": 750.42, "StatTrak\u2122 FactoryNew": 310.44, "MinimalWear": 792.38, "StatTrak\u2122 MinimalWear": 546.972, "FieldTested": 720.97, "StatTrak\u2122 FieldTested": 494.61599999999993, "WellWorn": 686.86, "StatTrak\u2122 WellWorn": 684.72, "BattleScarred": 720, "StatTrak\u2122 BattleScarred": 550.308, "totalItemValue": 709.5167859600002}, "M9 Bayonet | Blue Steel": {"FactoryNew": 1134.12, "StatTrak\u2122 FactoryNew": 1098.6119999999999, "MinimalWear": 1272.48, "StatTrak\u2122 MinimalWear": 805.7879999999999, "FieldTested": 1202.9699999999998, "StatTrak\u2122 FieldTested": 773.604, "WellWorn": 1101.08, "StatTrak\u2122 WellWorn": 753.756, "BattleScarred": 1036.07, "StatTrak\u2122 BattleScarred": 788.7719999999999, "totalItemValue": 1128.6605459999998}, "M9 Bayonet | Night": {"FactoryNew": 1122.792, "StatTrak\u2122 FactoryNew": 0, "MinimalWear": 1004.0399999999998, "StatTrak\u2122 MinimalWear": 1008.5899999999998, "FieldTested": 812.9199999999998, "StatTrak\u2122 FieldTested": 813.9499999999999, "WellWorn": 765.05, "StatTrak\u2122 WellWorn": 555.816, "BattleScarred": 779.9799999999999, "StatTrak\u2122 BattleScarred": 550.14, "totalItemValue": 831.986867}, "M9 Bayonet | Stained": {"FactoryNew": 800.3639999999999, "StatTrak\u2122 FactoryNew": 881.832, "MinimalWear": 992.5099999999999, "StatTrak\u2122 MinimalWear": 685.548, "FieldTested": 966.0899999999999, "StatTrak\u2122 FieldTested": 868.5099999999999, "WellWorn": 858.0799999999999, "StatTrak\u2122 WellWorn": 610.68, "BattleScarred": 839.6599999999999, "StatTrak\u2122 BattleScarred": 591.8159999999999, "totalItemValue": 901.0618919999998}, "M9 Bayonet | Urban Masked": {"FactoryNew": 709.56, "StatTrak\u2122 FactoryNew": 0, "MinimalWear": 563.9879999999999, "StatTrak\u2122 MinimalWear": 765.5699999999999, "FieldTested": 722.14, "StatTrak\u2122 FieldTested": 702.5799999999999, "WellWorn": 671.21, "StatTrak\u2122 WellWorn": 500.112, "BattleScarred": 530.292, "StatTrak\u2122 BattleScarred": 541.968, "totalItemValue": 664.5396699600001}, "M9 Bayonet | Forest DDPAT": {"FactoryNew": 1533.6299999999999, "StatTrak\u2122 FactoryNew": 0, "MinimalWear": 760.0999999999999, "StatTrak\u2122 MinimalWear": 700.3919999999999, "FieldTested": 709.0799999999999, "StatTrak\u2122 FieldTested": 704.55, "WellWorn": 641.8199999999999, "StatTrak\u2122 WellWorn": 518.808, "BattleScarred": 704.52, "StatTrak\u2122 BattleScarred": 525.3, "totalItemValue": 709.8320547600001}, "M9 Bayonet | Boreal Forest": {"FactoryNew": 783.7679999999999, "StatTrak\u2122 FactoryNew": 0, "MinimalWear": 764.39, "StatTrak\u2122 MinimalWear": 714.99, "FieldTested": 714.52, "StatTrak\u2122 FieldTested": 490.188, "WellWorn": 490.27199999999993, "StatTrak\u2122 WellWorn": 500.28, "BattleScarred": 709.87, "StatTrak\u2122 BattleScarred": 494.448, "totalItemValue": 684.71769762}, "M9 Bayonet | Safari Mesh": {"FactoryNew": 1348.596, "StatTrak\u2122 FactoryNew": 0, "MinimalWear": 700.67, "StatTrak\u2122 MinimalWear": 705.7499999999999, "FieldTested": 697.48, "StatTrak\u2122 FieldTested": 483.59999999999997, "WellWorn": 489.444, "StatTrak\u2122 WellWorn": 485.268, "BattleScarred": 695.18, "StatTrak\u2122 BattleScarred": 497.7, "totalItemValue": 666.38250516}}, "ItemCosts": {"Covert": {"SSG 08 | Blood in the Water": {"FactoryNew": 94.57, "StatTrak\u2122 FactoryNew": 597.63, "MinimalWear": 62.57, "StatTrak\u2122 MinimalWear": 232.47, "FieldTested": 45.048, "StatTrak\u2122 FieldTested": 237.16, "totalItemValue": 79.90065536}}, "Classified": {"P90 | Cold Blooded": {"FactoryNew": 83.94, "StatTrak\u2122 FactoryNew": 129.36999999999998, "MinimalWear": 93.13, "StatTrak\u2122 MinimalWear": 117.32, "totalItemValue": 88.744442}, "USP-S | Serum": {"FactoryNew": 78.32, "StatTrak\u2122 FactoryNew": 82.404, "MinimalWear": 58.48, "StatTrak\u2122 MinimalWear": 63.49, "FieldTested": 54.73, "StatTrak\u2122 FieldTested": 61.92, "totalItemValue": 67.448788}}, "Restricted": {"Five-SeveN | Case Hardened": {"FactoryNew": 27.340000000000003, "StatTrak\u2122 FactoryNew": 125.32, "MinimalWear": 17.09, "StatTrak\u2122 MinimalWear": 54.78, "FieldTested": 13.879999999999999, "StatTrak\u2122 FieldTested": 29.38, "WellWorn": 12.91, "StatTrak\u2122 WellWorn": 23.9, "BattleScarred": 13.28, "StatTrak\u2122 BattleScarred": 27.02, "totalItemValue": 16.918999999999997}, "MP9 | Hypnotic": {"FactoryNew": 14.58, "StatTrak\u2122 FactoryNew": 78.11999999999999, "MinimalWear": 14.99, "StatTrak\u2122 MinimalWear": 42.84, "totalItemValue": 20.817117}, "Nova | Graphite": {"FactoryNew": 12.3, "StatTrak\u2122 FactoryNew": 40.8, "MinimalWear": 11.7, "StatTrak\u2122 MinimalWear": 35.184, "totalItemValue": 15.013952400000003}, "Dual Berettas | Hemoglobin": {"FactoryNew": 14.3, "StatTrak\u2122 FactoryNew": 36.64, "MinimalWear": 12.46, "StatTrak\u2122 MinimalWear": 27.83, "FieldTested": 12.4, "StatTrak\u2122 FieldTested": 26.06, "totalItemValue": 15.387917900000003}}, "Mil_Spec": {"SCAR-20 | Crimson Web": {"FactoryNew": 21.852, "StatTrak\u2122 FactoryNew": 67.61, "MinimalWear": 7.61, "StatTrak\u2122 MinimalWear": 10.176, "FieldTested": 6.510000000000001, "StatTrak\u2122 FieldTested": 7.23, "WellWorn": 6.432, "StatTrak\u2122 WellWorn": 6.768000000000001, "BattleScarred": 5.99, "StatTrak\u2122 BattleScarred": 5.94, "totalItemValue": 6.816719840000001}, "M4A1-S | Blood Tiger": {"FactoryNew": 8.68, "StatTrak\u2122 FactoryNew": 21.159999999999997, "MinimalWear": 7.72, "StatTrak\u2122 MinimalWear": 16.52, "FieldTested": 7.5600000000000005, "StatTrak\u2122 FieldTested": 16.43, "totalItemValue": 9.081980699999999}, "Tec-9 | Blue Titanium": {"FactoryNew": 10.02, "StatTrak\u2122 FactoryNew": 14.74, "totalItemValue": 10.492}, "P250 | Hive": {"FactoryNew": 7.8100000000000005, "StatTrak\u2122 FactoryNew": 11.55, "MinimalWear": 5.81, "StatTrak\u2122 MinimalWear": 9.41, "FieldTested": 5.58, "StatTrak\u2122 FieldTested": 9.18, "totalItemValue": 6.901257}, "FAMAS | Hexane": {"FactoryNew": 7, "StatTrak\u2122 FactoryNew": 10.67, "MinimalWear": 5.99, "StatTrak\u2122 MinimalWear": 8.484, "FieldTested": 5.78, "StatTrak\u2122 FieldTested": 7.548, "WellWorn": 5.268, "StatTrak\u2122 WellWorn": 8.472, "totalItemValue": 6.44861118}}}, "KnifeEstimates": {"Bayonet | Fade": {"FactoryNew": true, "StatTrak\u2122 FactoryNew": false, "MinimalWear": true, "StatTrak\u2122 MinimalWear": true}, "Bayonet | \u2605 (Vanilla)": {"Normal": false, "StatTrak\u2122 Normal": false}, "Bayonet | Slaughter": {"FactoryNew": false, "StatTrak\u2122 FactoryNew": true, "MinimalWear": false, "StatTrak\u2122 MinimalWear": true, "FieldTested": true, "StatTrak\u2122 FieldTested": true}, "Bayonet | Case Hardened": {"FactoryNew": false, "StatTrak\u2122 FactoryNew": true, "MinimalWear": false, "StatTrak\u2122 MinimalWear": true, "FieldTested": false, "StatTrak\u2122 FieldTested": true, "WellWorn": false, "StatTrak\u2122 WellWorn": true, "BattleScarred": false, "StatTrak\u2122 BattleScarred": true}, "Bayonet | Crimson Web": {"FactoryNew": true, "StatTrak\u2122 FactoryNew": true, "MinimalWear": false, "StatTrak\u2122 MinimalWear": true, "FieldTested": false, "StatTrak\u2122 FieldTested": false, "WellWorn": true, "StatTrak\u2122 WellWorn": true, "BattleScarred": true, "StatTrak\u2122 BattleScarred": true}, "Bayonet | Night": {"FactoryNew": true, "StatTrak\u2122 FactoryNew": true, "MinimalWear": false, "StatTrak\u2122 MinimalWear": true, "FieldTested": false, "StatTrak\u2122 FieldTested": true, "WellWorn": false, "StatTrak\u2122 WellWorn": true, "BattleScarred": false, "StatTrak\u2122 BattleScarred": true}, "Bayonet | Blue Steel": {"FactoryNew": true, "StatTrak\u2122 FactoryNew": true, "MinimalWear": false, "StatTrak\u2122 MinimalWear": true, "FieldTested": false, "StatTrak\u2122 FieldTested": true, "WellWorn": false, "StatTrak\u2122 WellWorn": true, "BattleScarred": false, "StatTrak\u2122 BattleScarred": true}, "Bayonet | Stained": {"FactoryNew": true, "StatTrak\u2122 FactoryNew": true, "MinimalWear": false, "StatTrak\u2122 MinimalWear": true, "FieldTested": false, "StatTrak\u2122 FieldTested": true, "WellWorn": false, "StatTrak\u2122 WellWorn": true, "BattleScarred": false, "StatTrak\u2122 BattleScarred": true}, "Bayonet | Boreal Forest": {"FactoryNew": true, "StatTrak\u2122 FactoryNew": true, "MinimalWear": false, "StatTrak\u2122 MinimalWear": true, "FieldTested": false, "StatTrak\u2122 FieldTested": true, "WellWorn": false, "StatTrak\u2122 WellWorn": true, "BattleScarred": true, "StatTrak\u2122 BattleScarred": true}, "Bayonet | Urban Masked": {"FactoryNew": true, "StatTrak\u2122 FactoryNew": true, "MinimalWear": false, "StatTrak\u2122 MinimalWear": true, "FieldTested": false, "StatTrak\u2122 FieldTested": false, "WellWorn": false, "StatTrak\u2122 WellWorn": true, "BattleScarred": false, "StatTrak\u2122 BattleScarred": true}, "Bayonet | Forest DDPAT": {"FactoryNew": true, "StatTrak\u2122 FactoryNew": true, "MinimalWear": false, "StatTrak\u2122 MinimalWear": true, "FieldTested": false, "StatTrak\u2122 FieldTested": true, "WellWorn": true, "StatTrak\u2122 WellWorn": true, "BattleScarred": false, "StatTrak\u2122 BattleScarred": true}, "Bayonet | Scorched": {"FactoryNew": true, "StatTrak\u2122 FactoryNew": true, "MinimalWear": false, "StatTrak\u2122 MinimalWear": true, "FieldTested": false, "StatTrak\u2122 FieldTested": true, "WellWorn": true, "StatTrak\u2122 WellWorn": true, "BattleScarred": false, "StatTrak\u2122 BattleScarred": true}, "Bayonet | Safari Mesh": {"FactoryNew": true, "StatTrak\u2122 FactoryNew": true, "MinimalWear": false, "StatTrak\u2122 MinimalWear": true, "FieldTested": false, "StatTrak\u2122 FieldTested": true, "WellWorn": false, "StatTrak\u2122 WellWorn": true, "BattleScarred": false, "StatTrak\u2122 BattleScarred": true}, "Flip Knife | Fade": {"FactoryNew": true, "StatTrak\u2122 FactoryNew": true, "MinimalWear": true, "StatTrak\u2122 MinimalWear": true}, "Flip Knife | Slaughter": {"FactoryNew": false, "StatTrak\u2122 FactoryNew": true, "MinimalWear": false, "StatTrak\u2122 MinimalWear": true, "FieldTested": false, "StatTrak\u2122 FieldTested": true}, "Flip Knife | Crimson Web": {"FactoryNew": true, "StatTrak\u2122 FactoryNew": true, "MinimalWear": false, "StatTrak\u2122 MinimalWear": true, "FieldTested": false, "StatTrak\u2122 FieldTested": false, "WellWorn": false, "StatTrak\u2122 WellWorn": true, "BattleScarred": false, "StatTrak\u2122 BattleScarred": true}, "Flip Knife | Case Hardened": {"FactoryNew": true, "StatTrak\u2122 FactoryNew": true, "MinimalWear": true, "StatTrak\u2122 MinimalWear": true, "FieldTested": false, "StatTrak\u2122 FieldTested": false, "WellWorn": false, "StatTrak\u2122 WellWorn": true, "BattleScarred": false, "StatTrak\u2122 BattleScarred": true}, "Flip Knife | \u2605 (Vanilla)": {"Normal": true, "StatTrak\u2122 Normal": true}, "Flip Knife | Urban Masked": {"FactoryNew": true, "StatTrak\u2122 FactoryNew": true, "MinimalWear": false, "StatTrak\u2122 MinimalWear": true, "FieldTested": false, "StatTrak\u2122 FieldTested": true, "WellWorn": false, "StatTrak\u2122 WellWorn": true, "BattleScarred": false, "StatTrak\u2122 BattleScarred": true}, "Flip Knife | Night": {"FactoryNew": true, "StatTrak\u2122 FactoryNew": true, "MinimalWear": false, "StatTrak\u2122 MinimalWear": true, "FieldTested": false, "StatTrak\u2122 FieldTested": true, "WellWorn": true, "StatTrak\u2122 WellWorn": true, "BattleScarred": false, "StatTrak\u2122 BattleScarred": true}, "Flip Knife | Blue Steel": {"FactoryNew": true, "StatTrak\u2122 FactoryNew": true, "MinimalWear": false, "StatTrak\u2122 MinimalWear": true, "FieldTested": false, "StatTrak\u2122 FieldTested": true, "WellWorn": false, "StatTrak\u2122 WellWorn": true, "BattleScarred": false, "StatTrak\u2122 BattleScarred": true}, "Flip Knife | Stained": {"FactoryNew": true, "StatTrak\u2122 FactoryNew": true, "MinimalWear": false, "StatTrak\u2122 MinimalWear": true, "FieldTested": false, "StatTrak\u2122 FieldTested": true, "WellWorn": false, "StatTrak\u2122 WellWorn": true, "BattleScarred": false, "StatTrak\u2122 BattleScarred": true}, "Flip Knife | Safari Mesh": {"FactoryNew": true, "StatTrak\u2122 FactoryNew": true, "MinimalWear": false, "StatTrak\u2122 MinimalWear": true, "FieldTested": false, "StatTrak\u2122 FieldTested": false, "WellWorn": true, "StatTrak\u2122 WellWorn": true, "BattleScarred": false, "StatTrak\u2122 BattleScarred": true}, "Flip Knife | Boreal Forest": {"FactoryNew": true, "StatTrak\u2122 FactoryNew": true, "MinimalWear": false, "StatTrak\u2122 MinimalWear": true, "FieldTested": false, "StatTrak\u2122 FieldTested": false, "WellWorn": false, "StatTrak\u2122 WellWorn": true, "BattleScarred": false, "StatTrak\u2122 BattleScarred": true}, "Flip Knife | Forest DDPAT": {"FactoryNew": true, "StatTrak\u2122 FactoryNew": true, "MinimalWear": false, "StatTrak\u2122 MinimalWear": true, "FieldTested": false, "StatTrak\u2122 FieldTested": true, "WellWorn": false, "StatTrak\u2122 WellWorn": true, "BattleScarred": false, "StatTrak\u2122 BattleScarred": true}, "Flip Knife | Scorched": {"FactoryNew": true, "StatTrak\u2122 FactoryNew": true, "MinimalWear": false, "StatTrak\u2122 MinimalWear": true, "FieldTested": false, "StatTrak\u2122 FieldTested": false, "WellWorn": true, "StatTrak\u2122 WellWorn": true, "BattleScarred": false, "StatTrak\u2122 BattleScarred": true}, "Gut Knife | Fade": {"FactoryNew": false, "StatTrak\u2122 FactoryNew": false, "MinimalWear": true, "StatTrak\u2122 MinimalWear": true}, "Gut Knife | Case Hardened": {"FactoryNew": true, "StatTrak\u2122 FactoryNew": true, "MinimalWear": false, "StatTrak\u2122 MinimalWear": true, "FieldTested": false, "StatTrak\u2122 FieldTested": true, "WellWorn": false, "StatTrak\u2122 WellWorn": true, "BattleScarred": false, "StatTrak\u2122 BattleScarred": true}, "Gut Knife | Crimson Web": {"FactoryNew": true, "StatTrak\u2122 FactoryNew": true, "MinimalWear": false, "StatTrak\u2122 MinimalWear": true, "FieldTested": false, "StatTrak\u2122 FieldTested": false, "WellWorn": false, "StatTrak\u2122 WellWorn": true, "BattleScarred": false, "StatTrak\u2122 BattleScarred": true}, "Gut Knife | Slaughter": {"FactoryNew": false, "StatTrak\u2122 FactoryNew": true, "MinimalWear": false, "StatTrak\u2122 MinimalWear": true, "FieldTested": false, "StatTrak\u2122 FieldTested": true}, "Gut Knife | \u2605 (Vanilla)": {"Normal": false, "StatTrak\u2122 Normal": false}, "Gut Knife | Urban Masked": {"FactoryNew": true, "StatTrak\u2122 FactoryNew": true, "MinimalWear": false, "StatTrak\u2122 MinimalWear": true, "FieldTested": false, "StatTrak\u2122 FieldTested": true, "WellWorn": true, "StatTrak\u2122 WellWorn": true, "BattleScarred": true, "StatTrak\u2122 BattleScarred": true}, "Gut Knife | Safari Mesh": {"FactoryNew": true, "StatTrak\u2122 FactoryNew": true, "MinimalWear": false, "StatTrak\u2122 MinimalWear": true, "FieldTested": false, "StatTrak\u2122 FieldTested": true, "WellWorn": true, "StatTrak\u2122 WellWorn": true, "BattleScarred": false, "StatTrak\u2122 BattleScarred": true}, "Gut Knife | Blue Steel": {"FactoryNew": true, "StatTrak\u2122 FactoryNew": true, "MinimalWear": true, "StatTrak\u2122 MinimalWear": true, "FieldTested": false, "StatTrak\u2122 FieldTested": true, "WellWorn": false, "StatTrak\u2122 WellWorn": true, "BattleScarred": false, "StatTrak\u2122 BattleScarred": true}, "Gut Knife | Night": {"FactoryNew": true, "StatTrak\u2122 FactoryNew": true, "MinimalWear": false, "StatTrak\u2122 MinimalWear": true, "FieldTested": false, "StatTrak\u2122 FieldTested": true, "WellWorn": true, "StatTrak\u2122 WellWorn": true, "BattleScarred": false, "StatTrak\u2122 BattleScarred": true}, "Gut Knife | Stained": {"FactoryNew": true, "StatTrak\u2122 FactoryNew": true, "MinimalWear": false, "StatTrak\u2122 MinimalWear": true, "FieldTested": false, "StatTrak\u2122 FieldTested": true, "WellWorn": false, "StatTrak\u2122 WellWorn": true, "BattleScarred": false, "StatTrak\u2122 BattleScarred": true}, "Gut Knife | Forest DDPAT": {"FactoryNew": true, "StatTrak\u2122 FactoryNew": true, "MinimalWear": false, "StatTrak\u2122 MinimalWear": true, "FieldTested": false, "StatTrak\u2122 FieldTested": true, "WellWorn": true, "StatTrak\u2122 WellWorn": true, "BattleScarred": false, "StatTrak\u2122 BattleScarred": true}, "Gut Knife | Scorched": {"FactoryNew": true, "StatTrak\u2122 FactoryNew": true, "MinimalWear": false, "StatTrak\u2122 MinimalWear": true, "FieldTested": false, "StatTrak\u2122 FieldTested": true, "WellWorn": true, "StatTrak\u2122 WellWorn": true, "BattleScarred": true, "StatTrak\u2122 BattleScarred": true}, "Gut Knife | Boreal Forest": {"FactoryNew": true, "StatTrak\u2122 FactoryNew": true, "MinimalWear": false, "StatTrak\u2122 MinimalWear": true, "FieldTested": false, "StatTrak\u2122 FieldTested": true, "WellWorn": true, "StatTrak\u2122 WellWorn": true, "BattleScarred": false, "StatTrak\u2122 BattleScarred": true}, "Karambit | Slaughter": {"FactoryNew": true, "StatTrak\u2122 FactoryNew": true, "MinimalWear": false, "StatTrak\u2122 MinimalWear": true, "FieldTested": true, "StatTrak\u2122 FieldTested": true}, "Karambit | \u2605 (Vanilla)": {"Normal": true, "StatTrak\u2122 Normal": true}, "Karambit | Case Hardened": {"FactoryNew": true, "StatTrak\u2122 FactoryNew": true, "MinimalWear": true, "StatTrak\u2122 MinimalWear": true, "FieldTested": false, "StatTrak\u2122 FieldTested": true, "WellWorn": true, "StatTrak\u2122 WellWorn": true, "BattleScarred": false, "StatTrak\u2122 BattleScarred": true}, "Karambit | Crimson Web": {"FactoryNew": true, "StatTrak\u2122 FactoryNew": true, "MinimalWear": true, "StatTrak\u2122 MinimalWear": true, "FieldTested": false, "StatTrak\u2122 FieldTested": true, "WellWorn": false, "StatTrak\u2122 WellWorn": true, "BattleScarred": false, "StatTrak\u2122 BattleScarred": true}, "Karambit | Blue Steel": {"FactoryNew": true, "StatTrak\u2122 FactoryNew": true, "MinimalWear": true, "StatTrak\u2122 MinimalWear": true, "FieldTested": false, "StatTrak\u2122 FieldTested": true, "WellWorn": true, "StatTrak\u2122 WellWorn": true, "BattleScarred": false, "StatTrak\u2122 BattleScarred": true}, "Karambit | Stained": {"FactoryNew": true, "StatTrak\u2122 FactoryNew": true, "MinimalWear": false, "StatTrak\u2122 MinimalWear": true, "FieldTested": false, "StatTrak\u2122 FieldTested": true, "WellWorn": false, "StatTrak\u2122 WellWorn": true, "BattleScarred": false, "StatTrak\u2122 BattleScarred": true}, "Karambit | Night": {"FactoryNew": true, "StatTrak\u2122 FactoryNew": true, "MinimalWear": true, "StatTrak\u2122 MinimalWear": true, "FieldTested": false, "StatTrak\u2122 FieldTested": true, "WellWorn": false, "StatTrak\u2122 WellWorn": true, "BattleScarred": false, "StatTrak\u2122 BattleScarred": true}, "Karambit | Boreal Forest": {"FactoryNew": true, "StatTrak\u2122 FactoryNew": true, "MinimalWear": false, "StatTrak\u2122 MinimalWear": true, "FieldTested": false, "StatTrak\u2122 FieldTested": true, "WellWorn": true, "StatTrak\u2122 WellWorn": true, "BattleScarred": true, "StatTrak\u2122 BattleScarred": true}, "Karambit | Urban Masked": {"FactoryNew": true, "StatTrak\u2122 FactoryNew": true, "MinimalWear": false, "StatTrak\u2122 MinimalWear": true, "FieldTested": false, "StatTrak\u2122 FieldTested": true, "WellWorn": true, "StatTrak\u2122 WellWorn": true, "BattleScarred": true, "StatTrak\u2122 BattleScarred": true}, "Karambit | Scorched": {"FactoryNew": true, "StatTrak\u2122 FactoryNew": true, "MinimalWear": false, "StatTrak\u2122 MinimalWear": true, "FieldTested": false, "StatTrak\u2122 FieldTested": true, "WellWorn": true, "StatTrak\u2122 WellWorn": true, "BattleScarred": false, "StatTrak\u2122 BattleScarred": true}, "Karambit | Forest DDPAT": {"FactoryNew": true, "StatTrak\u2122 FactoryNew": true, "MinimalWear": true, "StatTrak\u2122 MinimalWear": true, "FieldTested": false, "StatTrak\u2122 FieldTested": false, "WellWorn": true, "StatTrak\u2122 WellWorn": true, "BattleScarred": false, "StatTrak\u2122 BattleScarred": true}, "Karambit | Safari Mesh": {"FactoryNew": true, "StatTrak\u2122 FactoryNew": true, "MinimalWear": true, "StatTrak\u2122 MinimalWear": true, "FieldTested": false, "StatTrak\u2122 FieldTested": false, "WellWorn": false, "StatTrak\u2122 WellWorn": true, "BattleScarred": true, "StatTrak\u2122 BattleScarred": true}, "Karambit | Fade": {"FactoryNew": true, "StatTrak\u2122 FactoryNew": true, "MinimalWear": true, "StatTrak\u2122 MinimalWear": true}, "M9 Bayonet | Fade": {"FactoryNew": true, "StatTrak\u2122 FactoryNew": true, "MinimalWear": true, "StatTrak\u2122 MinimalWear": true}, "M9 Bayonet | \u2605 (Vanilla)": {"Normal": false, "StatTrak\u2122 Normal": true}, "M9 Bayonet | Slaughter": {"FactoryNew": true, "StatTrak\u2122 FactoryNew": true, "MinimalWear": false, "StatTrak\u2122 MinimalWear": true, "FieldTested": false, "StatTrak\u2122 FieldTested": true}, "M9 Bayonet | Crimson Web": {"FactoryNew": true, "StatTrak\u2122 FactoryNew": true, "MinimalWear": false, "StatTrak\u2122 MinimalWear": true, "FieldTested": false, "StatTrak\u2122 FieldTested": false, "WellWorn": false, "StatTrak\u2122 WellWorn": true, "BattleScarred": false, "StatTrak\u2122 BattleScarred": true}, "M9 Bayonet | Case Hardened": {"FactoryNew": true, "StatTrak\u2122 FactoryNew": true, "MinimalWear": false, "StatTrak\u2122 MinimalWear": false, "FieldTested": true, "StatTrak\u2122 FieldTested": true, "WellWorn": false, "StatTrak\u2122 WellWorn": true, "BattleScarred": true, "StatTrak\u2122 BattleScarred": true}, "M9 Bayonet | Scorched": {"FactoryNew": true, "StatTrak\u2122 FactoryNew": true, "MinimalWear": false, "StatTrak\u2122 MinimalWear": true, "FieldTested": false, "StatTrak\u2122 FieldTested": true, "WellWorn": true, "StatTrak\u2122 WellWorn": true, "BattleScarred": true, "StatTrak\u2122 BattleScarred": true}, "M9 Bayonet | Blue Steel": {"FactoryNew": true, "StatTrak\u2122 FactoryNew": true, "MinimalWear": true, "StatTrak\u2122 MinimalWear": true, "FieldTested": false, "StatTrak\u2122 FieldTested": true, "WellWorn": false, "StatTrak\u2122 WellWorn": true, "BattleScarred": false, "StatTrak\u2122 BattleScarred": true}, "M9 Bayonet | Night": {"FactoryNew": true, "StatTrak\u2122 FactoryNew": true, "MinimalWear": false, "StatTrak\u2122 MinimalWear": true, "FieldTested": false, "StatTrak\u2122 FieldTested": true, "WellWorn": true, "StatTrak\u2122 WellWorn": true, "BattleScarred": false, "StatTrak\u2122 BattleScarred": true}, "M9 Bayonet | Stained": {"FactoryNew": true, "StatTrak\u2122 FactoryNew": true, "MinimalWear": false, "StatTrak\u2122 MinimalWear": true, "FieldTested": false, "StatTrak\u2122 FieldTested": true, "WellWorn": false, "StatTrak\u2122 WellWorn": true, "BattleScarred": false, "StatTrak\u2122 BattleScarred": true}, "M9 Bayonet | Urban Masked": {"FactoryNew": true, "StatTrak\u2122 FactoryNew": true, "MinimalWear": true, "StatTrak\u2122 MinimalWear": true, "FieldTested": false, "StatTrak\u2122 FieldTested": true, "WellWorn": false, "StatTrak\u2122 WellWorn": true, "BattleScarred": true, "StatTrak\u2122 BattleScarred": true}, "M9 Bayonet | Forest DDPAT": {"FactoryNew": true, "StatTrak\u2122 FactoryNew": true, "MinimalWear": false, "StatTrak\u2122 MinimalWear": true, "FieldTested": false, "StatTrak\u2122 FieldTested": true, "WellWorn": false, "StatTrak\u2122 WellWorn": true, "BattleScarred": false, "StatTrak\u2122 BattleScarred": true}, "M9 Bayonet | Boreal Forest": {"FactoryNew": true, "StatTrak\u2122 FactoryNew": true, "MinimalWear": false, "StatTrak\u2122 MinimalWear": true, "FieldTested": false, "StatTrak\u2122 FieldTested": true, "WellWorn": true, "StatTrak\u2122 WellWorn": true, "BattleScarred": true, "StatTrak\u2122 BattleScarred": true}, "M9 Bayonet | Safari Mesh": {"FactoryNew": true, "StatTrak\u2122 FactoryNew": true, "MinimalWear": false, "StatTrak\u2122 MinimalWear": true, "FieldTested": false, "StatTrak\u2122 FieldTested": true, "WellWorn": true, "StatTrak\u2122 WellWorn": true, "BattleScarred": false, "StatTrak\u2122 BattleScarred": true}}, "ItemEstimates": {"Covert": {"SSG 08 | Blood in the Water": {"FactoryNew": false, "StatTrak\u2122 FactoryNew": false, "MinimalWear": false, "StatTrak\u2122 MinimalWear": true, "FieldTested": true, "StatTrak\u2122 FieldTested": true}}, "Classified": {"P90 | Cold Blooded": {"FactoryNew": false, "StatTrak\u2122 FactoryNew": false, "MinimalWear": false, "StatTrak\u2122 MinimalWear": true}, "USP-S | Serum": {"FactoryNew": false, "StatTrak\u2122 FactoryNew": true, "MinimalWear": false, "StatTrak\u2122 MinimalWear": false, "FieldTested": false, "StatTrak\u2122 FieldTested": true}}, "Restricted": {"Five-SeveN | Case Hardened": {"FactoryNew": false, "StatTrak\u2122 FactoryNew": false, "MinimalWear": false, "StatTrak\u2122 MinimalWear": false, "FieldTested": false, "StatTrak\u2122 FieldTested": false, "WellWorn": false, "StatTrak\u2122 WellWorn": false, "BattleScarred": false, "StatTrak\u2122 BattleScarred": false}, "MP9 | Hypnotic": {"FactoryNew": false, "StatTrak\u2122 FactoryNew": false, "MinimalWear": false, "StatTrak\u2122 MinimalWear": false}, "Nova | Graphite": {"FactoryNew": false, "StatTrak\u2122 FactoryNew": false, "MinimalWear": true, "StatTrak\u2122 MinimalWear": true}, "Dual Berettas | Hemoglobin": {"FactoryNew": false, "StatTrak\u2122 FactoryNew": false, "MinimalWear": false, "StatTrak\u2122 MinimalWear": false, "FieldTested": false, "StatTrak\u2122 FieldTested": true}}, "Mil_Spec": {"SCAR-20 | Crimson Web": {"FactoryNew": true, "StatTrak\u2122 FactoryNew": true, "MinimalWear": false, "StatTrak\u2122 MinimalWear": true, "FieldTested": false, "StatTrak\u2122 FieldTested": false, "WellWorn": true, "StatTrak\u2122 WellWorn": true, "BattleScarred": true, "StatTrak\u2122 BattleScarred": true}, "M4A1-S | Blood Tiger": {"FactoryNew": false, "StatTrak\u2122 FactoryNew": false, "MinimalWear": false, "StatTrak\u2122 MinimalWear": false, "FieldTested": false, "StatTrak\u2122 FieldTested": false}, "Tec-9 | Blue Titanium": {"FactoryNew": false, "StatTrak\u2122 FactoryNew": false}, "P250 | Hive": {"FactoryNew": false, "StatTrak\u2122 FactoryNew": false, "MinimalWear": false, "StatTrak\u2122 MinimalWear": false, "FieldTested": false, "StatTrak\u2122 FieldTested": true}, "FAMAS | Hexane": {"FactoryNew": false, "StatTrak\u2122 FactoryNew": false, "MinimalWear": false, "StatTrak\u2122 MinimalWear": true, "FieldTested": false, "StatTrak\u2122 FieldTested": true, "WellWorn": true, "StatTrak\u2122 WellWorn": true}}}, "Items": {"SSG 08 | Blood in the Water": {"Name": "SSG 08 | Blood in the Water", "FloatMin": 6, "FloatMax": 20, "ImageUrl": "https://steamcdn-a.akamaihd.net/apps/730/icons/econ/default_generated/weapon_ssg08_cu_shark_light_large.00812c20a896847013b0a2913a166f6ba220a258.png", "Variations": 1, "Rarity": 11, "IsKnife": false, "ItemCollectionId": 16}, "P90 | Cold Blooded": {"Name": "P90 | Cold Blooded", "FloatMin": 0, "FloatMax": 8, "ImageUrl": "https://steamcdn-a.akamaihd.net/apps/730/icons/econ/default_generated/weapon_p90_am_slither_p90_light_large.583a90c66858cf0cc20253d2f4a0be1168eadbca.png", "Variations": 1, "Rarity": 8, "IsKnife": false, "ItemCollectionId": 16}, "USP-S | Serum": {"Name": "USP-S | Serum", "FloatMin": 0, "FloatMax": 25, "ImageUrl": "https://steamcdn-a.akamaihd.net/apps/730/icons/econ/default_generated/weapon_usp_silencer_am_electric_red_light_large.ef8005beba74458fabbe8f664e0b210b2ef3a007.png", "Variations": 1, "Rarity": 8, "IsKnife": false, "ItemCollectionId": 16}, "Five-SeveN | Case Hardened": {"Name": "Five-SeveN | Case Hardened", "FloatMin": 0, "FloatMax": 100, "ImageUrl": "https://steamcdn-a.akamaihd.net/apps/730/icons/econ/default_generated/weapon_fiveseven_aq_oiled_light_large.fdaa095453965b2be93f8aa90ae469d926fac4e7.png", "Variations": 1, "Rarity": 5, "IsKnife": false, "ItemCollectionId": 16}, "MP9 | Hypnotic": {"Name": "MP9 | Hypnotic", "FloatMin": 0, "FloatMax": 8, "ImageUrl": "https://steamcdn-a.akamaihd.net/apps/730/icons/econ/default_generated/weapon_mp9_aa_vertigo_light_large.41a7195e0a6ba44c2fc64d64bee0635444b0c569.png", "Variations": 1, "Rarity": 5, "IsKnife": false, "ItemCollectionId": 16}, "Nova | Graphite": {"Name": "Nova | Graphite", "FloatMin": 0, "FloatMax": 12, "ImageUrl": "https://steamcdn-a.akamaihd.net/apps/730/icons/econ/default_generated/weapon_nova_am_crumple_light_large.e46bab0dc8f8fe10b83c18ed9f9d9945352781af.png", "Variations": 1, "Rarity": 5, "IsKnife": false, "ItemCollectionId": 16}, "Dual Berettas | Hemoglobin": {"Name": "Dual Berettas | Hemoglobin", "FloatMin": 0, "FloatMax": 20, "ImageUrl": "https://steamcdn-a.akamaihd.net/apps/730/icons/econ/default_generated/weapon_elite_am_ossify_red_light_large.9da21d3dc7b64952d853818075f524a9e4c1dfd3.png", "Variations": 1, "Rarity": 5, "IsKnife": false, "ItemCollectionId": 16}, "SCAR-20 | Crimson Web": {"Name": "SCAR-20 | Crimson Web", "FloatMin": 6, "FloatMax": 80, "ImageUrl": "https://steamcdn-a.akamaihd.net/apps/730/icons/econ/default_generated/weapon_scar20_hy_webs_darker_light_large.8e06e878c22b82c6bb1045f26e1bbc1926faecf2.png", "Variations": 1, "Rarity": 2, "IsKnife": false, "ItemCollectionId": 16}, "M4A1-S | Blood Tiger": {"Name": "M4A1-S | Blood Tiger", "FloatMin": 0, "FloatMax": 30, "ImageUrl": "https://steamcdn-a.akamaihd.net/apps/730/icons/econ/default_generated/weapon_m4a1_silencer_hy_redtiger_light_large.0b40a51b0020fa1781ddb7368e3b39c03263b2dd.png", "Variations": 1, "Rarity": 2, "IsKnife": false, "ItemCollectionId": 16}, "Tec-9 | Blue Titanium": {"Name": "Tec-9 | Blue Titanium", "FloatMin": 0, "FloatMax": 4, "ImageUrl": "https://steamcdn-a.akamaihd.net/apps/730/icons/econ/default_generated/weapon_tec9_an_titanium30v_light_large.76078065235a996df8184b684159dfee7efcd530.png", "Variations": 1, "Rarity": 2, "IsKnife": false, "ItemCollectionId": 16}, "P250 | Hive": {"Name": "P250 | Hive", "FloatMin": 0, "FloatMax": 30, "ImageUrl": "https://steamcdn-a.akamaihd.net/apps/730/icons/econ/default_generated/weapon_p250_hy_redhex_light_large.099092ccf56439b922b51569ce87f2f908abcc19.png", "Variations": 1, "Rarity": 2, "IsKnife": false, "ItemCollectionId": 16}, "FAMAS | Hexane": {"Name": "FAMAS | Hexane", "FloatMin": 0, "FloatMax": 40, "ImageUrl": "https://steamcdn-a.akamaihd.net/apps/730/icons/econ/default_generated/weapon_famas_hy_bluehex_light_large.fe87763b33ea8963cf87e9b8fd7b9bfc9014d747.png", "Variations": 1, "Rarity": 2, "IsKnife": false, "ItemCollectionId": 16}, "Bayonet | Fade": {"Name": "Bayonet | Fade", "FloatMin": 0, "FloatMax": 8, "ImageUrl": "https://steamcdn-a.akamaihd.net/apps/730/icons/econ/default_generated/weapon_bayonet_aa_fade_light_large.5ac4f422043b48b47e4453cc250c79fda3e78855.png", "Variations": 1, "Rarity": 11, "IsKnife": true, "ItemCollectionId": 16}, "Bayonet | \u2605 (Vanilla)": {"Name": "Bayonet | \u2605 (Vanilla)", "FloatMin": null, "FloatMax": null, "ImageUrl": "https://steamcdn-a.akamaihd.net/apps/730/icons/econ/weapons/base_weapons/weapon_bayonet.515de291204d6d896724d9fbb6856fcc6054a787.png", "Variations": 1, "Rarity": 11, "IsKnife": true, "ItemCollectionId": 16}, "Bayonet | Slaughter": {"Name": "Bayonet | Slaughter", "FloatMin": 1, "FloatMax": 26, "ImageUrl": "https://steamcdn-a.akamaihd.net/apps/730/icons/econ/default_generated/weapon_bayonet_am_zebra_light_large.2234064362204e87ea5ce3f997dc691d844d9168.png", "Variations": 1, "Rarity": 11, "IsKnife": true, "ItemCollectionId": 16}, "Bayonet | Case Hardened": {"Name": "Bayonet | Case Hardened", "FloatMin": 0, "FloatMax": 100, "ImageUrl": "https://steamcdn-a.akamaihd.net/apps/730/icons/econ/default_generated/weapon_bayonet_aq_oiled_light_large.920866e2a1f17fda7702e0b4cb95f45a8a8c0070.png", "Variations": 1, "Rarity": 11, "IsKnife": true, "ItemCollectionId": 16}, "Bayonet | Crimson Web": {"Name": "Bayonet | Crimson Web", "FloatMin": 6, "FloatMax": 80, "ImageUrl": "https://steamcdn-a.akamaihd.net/apps/730/icons/econ/default_generated/weapon_bayonet_hy_webs_light_large.9246001fd8c8b0c077dc2836ea7271a4a020750b.png", "Variations": 1, "Rarity": 11, "IsKnife": true, "ItemCollectionId": 16}, "Bayonet | Night": {"Name": "Bayonet | Night", "FloatMin": 6, "FloatMax": 80, "ImageUrl": "https://steamcdn-a.akamaihd.net/apps/730/icons/econ/default_generated/weapon_bayonet_so_night_light_large.11b2117af2e0f240111305857ab93e0091e347ed.png", "Variations": 1, "Rarity": 11, "IsKnife": true, "ItemCollectionId": 16}, "Bayonet | Blue Steel": {"Name": "Bayonet | Blue Steel", "FloatMin": 0, "FloatMax": 100, "ImageUrl": "https://steamcdn-a.akamaihd.net/apps/730/icons/econ/default_generated/weapon_bayonet_aq_blued_light_large.40905736c36dbdb9d08077ddaebb06cbb237f583.png", "Variations": 1, "Rarity": 11, "IsKnife": true, "ItemCollectionId": 16}, "Bayonet | Stained": {"Name": "Bayonet | Stained", "FloatMin": 0, "FloatMax": 100, "ImageUrl": "https://steamcdn-a.akamaihd.net/apps/730/icons/econ/default_generated/weapon_bayonet_aq_forced_light_large.460998cd194f90f65aec10ccaea8644b42430fc0.png", "Variations": 1, "Rarity": 11, "IsKnife": true, "ItemCollectionId": 16}, "Bayonet | Boreal Forest": {"Name": "Bayonet | Boreal Forest", "FloatMin": 6, "FloatMax": 80, "ImageUrl": "https://steamcdn-a.akamaihd.net/apps/730/icons/econ/default_generated/weapon_bayonet_hy_forest_boreal_light_large.4ecbfdb740d7345cb38430c1a4da15cec468b5ce.png", "Variations": 1, "Rarity": 11, "IsKnife": true, "ItemCollectionId": 16}, "Bayonet | Urban Masked": {"Name": "Bayonet | Urban Masked", "FloatMin": 6, "FloatMax": 80, "ImageUrl": "https://steamcdn-a.akamaihd.net/apps/730/icons/econ/default_generated/weapon_bayonet_sp_tape_urban_light_large.81c4d2a06c2d8c271a2b6de4bc47f0cb0d3f32be.png", "Variations": 1, "Rarity": 11, "IsKnife": true, "ItemCollectionId": 16}, "Bayonet | Forest DDPAT": {"Name": "Bayonet | Forest DDPAT", "FloatMin": 6, "FloatMax": 80, "ImageUrl": "https://steamcdn-a.akamaihd.net/apps/730/icons/econ/default_generated/weapon_bayonet_hy_ddpat_light_large.f53cb47d0ef8b431116008ec3896f8cedb712fb5.png", "Variations": 1, "Rarity": 11, "IsKnife": true, "ItemCollectionId": 16}, "Bayonet | Scorched": {"Name": "Bayonet | Scorched", "FloatMin": 6, "FloatMax": 80, "ImageUrl": "https://steamcdn-a.akamaihd.net/apps/730/icons/econ/default_generated/weapon_bayonet_sp_dapple_light_large.5c6962d79b65eb2053770a887facae88b361fcfe.png", "Variations": 1, "Rarity": 11, "IsKnife": true, "ItemCollectionId": 16}, "Bayonet | Safari Mesh": {"Name": "Bayonet | Safari Mesh", "FloatMin": 6, "FloatMax": 80, "ImageUrl": "https://steamcdn-a.akamaihd.net/apps/730/icons/econ/default_generated/weapon_bayonet_sp_mesh_tan_light_large.f0c1b71fd210b74b42dbf78253556e7ba9a99d15.png", "Variations": 1, "Rarity": 11, "IsKnife": true, "ItemCollectionId": 16}, "Flip Knife | Fade": {"Name": "Flip Knife | Fade", "FloatMin": 0, "FloatMax": 8, "ImageUrl": "https://steamcdn-a.akamaihd.net/apps/730/icons/econ/default_generated/weapon_knife_flip_aa_fade_light_large.811f8e8af2e00675c047a9c1e9f04bbe5ace83b1.png", "Variations": 1, "Rarity": 11, "IsKnife": true, "ItemCollectionId": 16}, "Flip Knife | Slaughter": {"Name": "Flip Knife | Slaughter", "FloatMin": 1, "FloatMax": 26, "ImageUrl": "https://steamcdn-a.akamaihd.net/apps/730/icons/econ/default_generated/weapon_knife_flip_am_zebra_light_large.55467fb65475d82c452bc96180d101ffd7e76192.png", "Variations": 1, "Rarity": 11, "IsKnife": true, "ItemCollectionId": 16}, "Flip Knife | Crimson Web": {"Name": "Flip Knife | Crimson Web", "FloatMin": 6, "FloatMax": 80, "ImageUrl": "https://steamcdn-a.akamaihd.net/apps/730/icons/econ/default_generated/weapon_knife_flip_hy_webs_light_large.e0bcc9e1d004bff0af07abc34a609c6654835ce6.png", "Variations": 1, "Rarity": 11, "IsKnife": true, "ItemCollectionId": 16}, "Flip Knife | Case Hardened": {"Name": "Flip Knife | Case Hardened", "FloatMin": 0, "FloatMax": 100, "ImageUrl": "https://steamcdn-a.akamaihd.net/apps/730/icons/econ/default_generated/weapon_knife_flip_aq_oiled_light_large.14589d4f366330490824f36e7f75219478e2cabd.png", "Variations": 1, "Rarity": 11, "IsKnife": true, "ItemCollectionId": 16}, "Flip Knife | \u2605 (Vanilla)": {"Name": "Flip Knife | \u2605 (Vanilla)", "FloatMin": null, "FloatMax": null, "ImageUrl": "https://steamcdn-a.akamaihd.net/apps/730/icons/econ/weapons/base_weapons/weapon_knife_flip.ebfc00735792b1e2947b30a321a07215dae8ceed.png", "Variations": 1, "Rarity": 11, "IsKnife": true, "ItemCollectionId": 16}, "Flip Knife | Urban Masked": {"Name": "Flip Knife | Urban Masked", "FloatMin": 6, "FloatMax": 80, "ImageUrl": "https://steamcdn-a.akamaihd.net/apps/730/icons/econ/default_generated/weapon_knife_flip_sp_tape_urban_light_large.bd1c04395ea024acb863acb628becf77edd4e4eb.png", "Variations": 1, "Rarity": 11, "IsKnife": true, "ItemCollectionId": 16}, "Flip Knife | Night": {"Name": "Flip Knife | Night", "FloatMin": 6, "FloatMax": 80, "ImageUrl": "https://steamcdn-a.akamaihd.net/apps/730/icons/econ/default_generated/weapon_knife_flip_so_night_light_large.cd613460bfdf848992e25f0a45aa3ab17b6d46b6.png", "Variations": 1, "Rarity": 11, "IsKnife": true, "ItemCollectionId": 16}, "Flip Knife | Blue Steel": {"Name": "Flip Knife | Blue Steel", "FloatMin": 0, "FloatMax": 100, "ImageUrl": "https://steamcdn-a.akamaihd.net/apps/730/icons/econ/default_generated/weapon_knife_flip_aq_blued_light_large.495efc692fdc551331e407697152d98c990272c3.png", "Variations": 1, "Rarity": 11, "IsKnife": true, "ItemCollectionId": 16}, "Flip Knife | Stained": {"Name": "Flip Knife | Stained", "FloatMin": 0, "FloatMax": 100, "ImageUrl": "https://steamcdn-a.akamaihd.net/apps/730/icons/econ/default_generated/weapon_knife_flip_aq_forced_light_large.e9a6576a928a11fc3771b302f2b66539db29b503.png", "Variations": 1, "Rarity": 11, "IsKnife": true, "ItemCollectionId": 16}, "Flip Knife | Safari Mesh": {"Name": "Flip Knife | Safari Mesh", "FloatMin": 6, "FloatMax": 80, "ImageUrl": "https://steamcdn-a.akamaihd.net/apps/730/icons/econ/default_generated/weapon_knife_flip_sp_mesh_tan_light_large.361c846ac7bce512f7077df8b8bd62da838ebe2e.png", "Variations": 1, "Rarity": 11, "IsKnife": true, "ItemCollectionId": 16}, "Flip Knife | Boreal Forest": {"Name": "Flip Knife | Boreal Forest", "FloatMin": 6, "FloatMax": 80, "ImageUrl": "https://steamcdn-a.akamaihd.net/apps/730/icons/econ/default_generated/weapon_knife_flip_hy_forest_boreal_light_large.d4878851507a64925cb11000bfdab55caeb3e07c.png", "Variations": 1, "Rarity": 11, "IsKnife": true, "ItemCollectionId": 16}, "Flip Knife | Forest DDPAT": {"Name": "Flip Knife | Forest DDPAT", "FloatMin": 6, "FloatMax": 80, "ImageUrl": "https://steamcdn-a.akamaihd.net/apps/730/icons/econ/default_generated/weapon_knife_flip_hy_ddpat_light_large.882d1120e7e558969121902d618da80b88105c3a.png", "Variations": 1, "Rarity": 11, "IsKnife": true, "ItemCollectionId": 16}, "Flip Knife | Scorched": {"Name": "Flip Knife | Scorched", "FloatMin": 6, "FloatMax": 80, "ImageUrl": "https://steamcdn-a.akamaihd.net/apps/730/icons/econ/default_generated/weapon_knife_flip_sp_dapple_light_large.fdfee11d1148f81582f438cf1fdf175717c71a0e.png", "Variations": 1, "Rarity": 11, "IsKnife": true, "ItemCollectionId": 16}, "Gut Knife | Fade": {"Name": "Gut Knife | Fade", "FloatMin": 0, "FloatMax": 8, "ImageUrl": "https://steamcdn-a.akamaihd.net/apps/730/icons/econ/default_generated/weapon_knife_gut_aa_fade_light_large.6e89c23706eafc34e7713c264fddeb94444a9b67.png", "Variations": 1, "Rarity": 11, "IsKnife": true, "ItemCollectionId": 16}, "Gut Knife | Case Hardened": {"Name": "Gut Knife | Case Hardened", "FloatMin": 0, "FloatMax": 100, "ImageUrl": "https://steamcdn-a.akamaihd.net/apps/730/icons/econ/default_generated/weapon_knife_gut_aq_oiled_light_large.f141737f74526886d0d4895281e9a57526314c5c.png", "Variations": 1, "Rarity": 11, "IsKnife": true, "ItemCollectionId": 16}, "Gut Knife | Crimson Web": {"Name": "Gut Knife | Crimson Web", "FloatMin": 6, "FloatMax": 80, "ImageUrl": "https://steamcdn-a.akamaihd.net/apps/730/icons/econ/default_generated/weapon_knife_gut_hy_webs_light_large.217a769ed0131db1d3aef5a40bc927d4470bb22d.png", "Variations": 1, "Rarity": 11, "IsKnife": true, "ItemCollectionId": 16}, "Gut Knife | Slaughter": {"Name": "Gut Knife | Slaughter", "FloatMin": 1, "FloatMax": 26, "ImageUrl": "https://steamcdn-a.akamaihd.net/apps/730/icons/econ/default_generated/weapon_knife_gut_am_zebra_light_large.c374f8e71f300e4351b680b6246da645d3dea01d.png", "Variations": 1, "Rarity": 11, "IsKnife": true, "ItemCollectionId": 16}, "Gut Knife | \u2605 (Vanilla)": {"Name": "Gut Knife | \u2605 (Vanilla)", "FloatMin": null, "FloatMax": null, "ImageUrl": "https://steamcdn-a.akamaihd.net/apps/730/icons/econ/weapons/base_weapons/weapon_knife_gut.1d53007384970e8eaf28448312777683fd633a79.png", "Variations": 1, "Rarity": 11, "IsKnife": true, "ItemCollectionId": 16}, "Gut Knife | Urban Masked": {"Name": "Gut Knife | Urban Masked", "FloatMin": 6, "FloatMax": 80, "ImageUrl": "https://steamcdn-a.akamaihd.net/apps/730/icons/econ/default_generated/weapon_knife_gut_sp_tape_urban_light_large.71f4811888602d3b48f35e030bd39ecbcac7f22e.png", "Variations": 1, "Rarity": 11, "IsKnife": true, "ItemCollectionId": 16}, "Gut Knife | Safari Mesh": {"Name": "Gut Knife | Safari Mesh", "FloatMin": 6, "FloatMax": 80, "ImageUrl": "https://steamcdn-a.akamaihd.net/apps/730/icons/econ/default_generated/weapon_knife_gut_sp_mesh_tan_light_large.5f58d777d76148ba031b587fff1b0b3465d2c441.png", "Variations": 1, "Rarity": 11, "IsKnife": true, "ItemCollectionId": 16}, "Gut Knife | Blue Steel": {"Name": "Gut Knife | Blue Steel", "FloatMin": 0, "FloatMax": 100, "ImageUrl": "https://steamcdn-a.akamaihd.net/apps/730/icons/econ/default_generated/weapon_knife_gut_aq_blued_light_large.0e40bb0e3eb5de3de1b925853e3e4ec755f9b65a.png", "Variations": 1, "Rarity": 11, "IsKnife": true, "ItemCollectionId": 16}, "Gut Knife | Night": {"Name": "Gut Knife | Night", "FloatMin": 6, "FloatMax": 80, "ImageUrl": "https://steamcdn-a.akamaihd.net/apps/730/icons/econ/default_generated/weapon_knife_gut_so_night_light_large.eec2bb404a436b6d74f19c72b88f70380ab31eee.png", "Variations": 1, "Rarity": 11, "IsKnife": true, "ItemCollectionId": 16}, "Gut Knife | Stained": {"Name": "Gut Knife | Stained", "FloatMin": 0, "FloatMax": 100, "ImageUrl": "https://steamcdn-a.akamaihd.net/apps/730/icons/econ/default_generated/weapon_knife_gut_aq_forced_light_large.3f5b057c710fc4403f54d3979f482f511eb69d8b.png", "Variations": 1, "Rarity": 11, "IsKnife": true, "ItemCollectionId": 16}, "Gut Knife | Forest DDPAT": {"Name": "Gut Knife | Forest DDPAT", "FloatMin": 6, "FloatMax": 80, "ImageUrl": "https://steamcdn-a.akamaihd.net/apps/730/icons/econ/default_generated/weapon_knife_gut_hy_ddpat_light_large.855f6ca62686c8f365e503d379b07b4c41a8658a.png", "Variations": 1, "Rarity": 11, "IsKnife": true, "ItemCollectionId": 16}, "Gut Knife | Scorched": {"Name": "Gut Knife | Scorched", "FloatMin": 6, "FloatMax": 80, "ImageUrl": "https://steamcdn-a.akamaihd.net/apps/730/icons/econ/default_generated/weapon_knife_gut_sp_dapple_light_large.657af646f54600080b5c5e79133410eb47397fd6.png", "Variations": 1, "Rarity": 11, "IsKnife": true, "ItemCollectionId": 16}, "Gut Knife | Boreal Forest": {"Name": "Gut Knife | Boreal Forest", "FloatMin": 6, "FloatMax": 80, "ImageUrl": "https://steamcdn-a.akamaihd.net/apps/730/icons/econ/default_generated/weapon_knife_gut_hy_forest_boreal_light_large.b28a4cfb134cd8be5da39f82db0df407577478e8.png", "Variations": 1, "Rarity": 11, "IsKnife": true, "ItemCollectionId": 16}, "Karambit | Slaughter": {"Name": "Karambit | Slaughter", "FloatMin": 1, "FloatMax": 26, "ImageUrl": "https://steamcdn-a.akamaihd.net/apps/730/icons/econ/default_generated/weapon_knife_karambit_am_zebra_light_large.88457fbeca42e9dc1767983c76219d34b46abf14.png", "Variations": 1, "Rarity": 11, "IsKnife": true, "ItemCollectionId": 16}, "Karambit | \u2605 (Vanilla)": {"Name": "Karambit | \u2605 (Vanilla)", "FloatMin": null, "FloatMax": null, "ImageUrl": "https://steamcdn-a.akamaihd.net/apps/730/icons/econ/weapons/base_weapons/weapon_knife_karambit.8b491b581a4b9c7b5298071425f2b29a39a2a12f.png", "Variations": 1, "Rarity": 11, "IsKnife": true, "ItemCollectionId": 16}, "Karambit | Case Hardened": {"Name": "Karambit | Case Hardened", "FloatMin": 0, "FloatMax": 100, "ImageUrl": "https://steamcdn-a.akamaihd.net/apps/730/icons/econ/default_generated/weapon_knife_karambit_aq_oiled_light_large.52f9229d2960f5557a893a99cc679f1181b48d98.png", "Variations": 1, "Rarity": 11, "IsKnife": true, "ItemCollectionId": 16}, "Karambit | Crimson Web": {"Name": "Karambit | Crimson Web", "FloatMin": 6, "FloatMax": 80, "ImageUrl": "https://steamcdn-a.akamaihd.net/apps/730/icons/econ/default_generated/weapon_knife_karambit_hy_webs_light_large.61217494aaae26081c31d87f15739f42b4c1444a.png", "Variations": 1, "Rarity": 11, "IsKnife": true, "ItemCollectionId": 16}, "Karambit | Blue Steel": {"Name": "Karambit | Blue Steel", "FloatMin": 0, "FloatMax": 100, "ImageUrl": "https://steamcdn-a.akamaihd.net/apps/730/icons/econ/default_generated/weapon_knife_karambit_aq_blued_light_large.14e928cdede91a05a47656bc1a470cd515b9d735.png", "Variations": 1, "Rarity": 11, "IsKnife": true, "ItemCollectionId": 16}, "Karambit | Stained": {"Name": "Karambit | Stained", "FloatMin": 0, "FloatMax": 100, "ImageUrl": "https://steamcdn-a.akamaihd.net/apps/730/icons/econ/default_generated/weapon_knife_karambit_aq_forced_light_large.548f11f88cda9d7dd2915bd53d17e319d28a60ed.png", "Variations": 1, "Rarity": 11, "IsKnife": true, "ItemCollectionId": 16}, "Karambit | Night": {"Name": "Karambit | Night", "FloatMin": 6, "FloatMax": 80, "ImageUrl": "https://steamcdn-a.akamaihd.net/apps/730/icons/econ/default_generated/weapon_knife_karambit_so_night_light_large.427484b82687b9eb24e38125f5ea9e983847f68f.png", "Variations": 1, "Rarity": 11, "IsKnife": true, "ItemCollectionId": 16}, "Karambit | Boreal Forest": {"Name": "Karambit | Boreal Forest", "FloatMin": 6, "FloatMax": 80, "ImageUrl": "https://steamcdn-a.akamaihd.net/apps/730/icons/econ/default_generated/weapon_knife_karambit_hy_forest_boreal_light_large.8be99b9b53275463ecac09d080359af3526c4e81.png", "Variations": 1, "Rarity": 11, "IsKnife": true, "ItemCollectionId": 16}, "Karambit | Urban Masked": {"Name": "Karambit | Urban Masked", "FloatMin": 6, "FloatMax": 80, "ImageUrl": "https://steamcdn-a.akamaihd.net/apps/730/icons/econ/default_generated/weapon_knife_karambit_sp_tape_urban_light_large.d36d1cf81823ad0463a42ff3a8d9b1aff4910a73.png", "Variations": 1, "Rarity": 11, "IsKnife": true, "ItemCollectionId": 16}, "Karambit | Scorched": {"Name": "Karambit | Scorched", "FloatMin": 6, "FloatMax": 80, "ImageUrl": "https://steamcdn-a.akamaihd.net/apps/730/icons/econ/default_generated/weapon_knife_karambit_sp_dapple_light_large.88adf51bc8d53efc0d8c04114bd03d388e00d2b8.png", "Variations": 1, "Rarity": 11, "IsKnife": true, "ItemCollectionId": 16}, "Karambit | Forest DDPAT": {"Name": "Karambit | Forest DDPAT", "FloatMin": 6, "FloatMax": 80, "ImageUrl": "https://steamcdn-a.akamaihd.net/apps/730/icons/econ/default_generated/weapon_knife_karambit_hy_ddpat_light_large.4ce3d0d597a1481ff4cdc9ecc8c171748d492832.png", "Variations": 1, "Rarity": 11, "IsKnife": true, "ItemCollectionId": 16}, "Karambit | Safari Mesh": {"Name": "Karambit | Safari Mesh", "FloatMin": 6, "FloatMax": 80, "ImageUrl": "https://steamcdn-a.akamaihd.net/apps/730/icons/econ/default_generated/weapon_knife_karambit_sp_mesh_tan_light_large.a2d4ccf9954b957c819ade72a1cbea7ca0f0ad1f.png", "Variations": 1, "Rarity": 11, "IsKnife": true, "ItemCollectionId": 16}, "Karambit | Fade": {"Name": "Karambit | Fade", "FloatMin": 0, "FloatMax": 8, "ImageUrl": "https://steamcdn-a.akamaihd.net/apps/730/icons/econ/default_generated/weapon_knife_karambit_aa_fade_light_large.c91680d753adc2fcc5ed2e45daf815f6d4ab50b7.png", "Variations": 1, "Rarity": 11, "IsKnife": true, "ItemCollectionId": 16}, "M9 Bayonet | Fade": {"Name": "M9 Bayonet | Fade", "FloatMin": 0, "FloatMax": 8, "ImageUrl": "https://steamcdn-a.akamaihd.net/apps/730/icons/econ/default_generated/weapon_knife_m9_bayonet_aa_fade_light_large.66027f3a763a8b0a89895f3bdd55485d21d8dcda.png", "Variations": 1, "Rarity": 11, "IsKnife": true, "ItemCollectionId": 16}, "M9 Bayonet | \u2605 (Vanilla)": {"Name": "M9 Bayonet | \u2605 (Vanilla)", "FloatMin": null, "FloatMax": null, "ImageUrl": "https://steamcdn-a.akamaihd.net/apps/730/icons/econ/weapons/base_weapons/weapon_knife_m9_bayonet.1a55109e0c88792e5d56ea04dc1f676e44f9dec2.png", "Variations": 1, "Rarity": 11, "IsKnife": true, "ItemCollectionId": 16}, "M9 Bayonet | Slaughter": {"Name": "M9 Bayonet | Slaughter", "FloatMin": 1, "FloatMax": 26, "ImageUrl": "https://steamcdn-a.akamaihd.net/apps/730/icons/econ/default_generated/weapon_knife_m9_bayonet_am_zebra_light_large.53f9641b2b66b6587f779e5f222cc98a48489a1e.png", "Variations": 1, "Rarity": 11, "IsKnife": true, "ItemCollectionId": 16}, "M9 Bayonet | Crimson Web": {"Name": "M9 Bayonet | Crimson Web", "FloatMin": 6, "FloatMax": 80, "ImageUrl": "https://steamcdn-a.akamaihd.net/apps/730/icons/econ/default_generated/weapon_knife_m9_bayonet_hy_webs_light_large.5beb986be2c0fd1a6dde6cc3f360fb1a4b77823d.png", "Variations": 1, "Rarity": 11, "IsKnife": true, "ItemCollectionId": 16}, "M9 Bayonet | Case Hardened": {"Name": "M9 Bayonet | Case Hardened", "FloatMin": 0, "FloatMax": 100, "ImageUrl": "https://steamcdn-a.akamaihd.net/apps/730/icons/econ/default_generated/weapon_knife_m9_bayonet_aq_oiled_light_large.75bfecf8e9073c05ba21251889b8d49889f90669.png", "Variations": 1, "Rarity": 11, "IsKnife": true, "ItemCollectionId": 16}, "M9 Bayonet | Scorched": {"Name": "M9 Bayonet | Scorched", "FloatMin": 6, "FloatMax": 80, "ImageUrl": "https://steamcdn-a.akamaihd.net/apps/730/icons/econ/default_generated/weapon_knife_m9_bayonet_sp_dapple_light_large.b810fef46499697606ff2c70139805beb784c5ae.png", "Variations": 1, "Rarity": 11, "IsKnife": true, "ItemCollectionId": 16}, "M9 Bayonet | Blue Steel": {"Name": "M9 Bayonet | Blue Steel", "FloatMin": 0, "FloatMax": 100, "ImageUrl": "https://steamcdn-a.akamaihd.net/apps/730/icons/econ/default_generated/weapon_knife_m9_bayonet_aq_blued_light_large.cf1eae5b0d42c0c265ee77addcd1207eba7a8a4b.png", "Variations": 1, "Rarity": 11, "IsKnife": true, "ItemCollectionId": 16}, "M9 Bayonet | Night": {"Name": "M9 Bayonet | Night", "FloatMin": 6, "FloatMax": 80, "ImageUrl": "https://steamcdn-a.akamaihd.net/apps/730/icons/econ/default_generated/weapon_knife_m9_bayonet_so_night_light_large.5acbbec44a12a3d5e53890c7a2e58aaf83ae2871.png", "Variations": 1, "Rarity": 11, "IsKnife": true, "ItemCollectionId": 16}, "M9 Bayonet | Stained": {"Name": "M9 Bayonet | Stained", "FloatMin": 0, "FloatMax": 100, "ImageUrl": "https://steamcdn-a.akamaihd.net/apps/730/icons/econ/default_generated/weapon_knife_m9_bayonet_aq_forced_light_large.e409b18452030f3efa41178b439556d6f067fa52.png", "Variations": 1, "Rarity": 11, "IsKnife": true, "ItemCollectionId": 16}, "M9 Bayonet | Urban Masked": {"Name": "M9 Bayonet | Urban Masked", "FloatMin": 6, "FloatMax": 80, "ImageUrl": "https://steamcdn-a.akamaihd.net/apps/730/icons/econ/default_generated/weapon_knife_m9_bayonet_sp_tape_urban_light_large.b940d9da196a99dfa10f08a89c6d2843b5844fef.png", "Variations": 1, "Rarity": 11, "IsKnife": true, "ItemCollectionId": 16}, "M9 Bayonet | Forest DDPAT": {"Name": "M9 Bayonet | Forest DDPAT", "FloatMin": 6, "FloatMax": 80, "ImageUrl": "https://steamcdn-a.akamaihd.net/apps/730/icons/econ/default_generated/weapon_knife_m9_bayonet_hy_ddpat_light_large.1f511e46981a71dc67aec2904af5c7a39de52268.png", "Variations": 1, "Rarity": 11, "IsKnife": true, "ItemCollectionId": 16}, "M9 Bayonet | Boreal Forest": {"Name": "M9 Bayonet | Boreal Forest", "FloatMin": 6, "FloatMax": 80, "ImageUrl": "https://steamcdn-a.akamaihd.net/apps/730/icons/econ/default_generated/weapon_knife_m9_bayonet_hy_forest_boreal_light_large.074a7a96a875a57e6ad16e8a678245f23e7d46bb.png", "Variations": 1, "Rarity": 11, "IsKnife": true, "ItemCollectionId": 16}, "M9 Bayonet | Safari Mesh": {"Name": "M9 Bayonet | Safari Mesh", "FloatMin": 6, "FloatMax": 80, "ImageUrl": "https://steamcdn-a.akamaihd.net/apps/730/icons/econ/default_generated/weapon_knife_m9_bayonet_sp_mesh_tan_light_large.10896c7c3028779b668885a229e5ba773637b69c.png", "Variations": 1, "Rarity": 11, "IsKnife": true, "ItemCollectionId": 16}}, "SouvenirPackId": null, "SouvenirPackName": null, "SouvenirPackImg": null}